{
  "type": "GROUP",
"name": "All Requests",
"path": "",
"pathFormatted": "group_missing-name-b06d1",
"stats": {
    "name": "All Requests",
    "numberOfRequests": {
        "total": 33,
        "ok": 32,
        "ko": 1
    },
    "minResponseTime": {
        "total": 29,
        "ok": 29,
        "ko": 5083
    },
    "maxResponseTime": {
        "total": 17909,
        "ok": 17909,
        "ko": 5083
    },
    "meanResponseTime": {
        "total": 2629,
        "ok": 2552,
        "ko": 5083
    },
    "standardDeviation": {
        "total": 4407,
        "ok": 4453,
        "ko": 0
    },
    "percentiles1": {
        "total": 853,
        "ok": 701,
        "ko": 5083
    },
    "percentiles2": {
        "total": 2526,
        "ok": 2378,
        "ko": 5083
    },
    "percentiles3": {
        "total": 13036,
        "ok": 13175,
        "ko": 5083
    },
    "percentiles4": {
        "total": 16884,
        "ok": 16916,
        "ko": 5083
    },
    "group1": {
    "name": "t < 800 ms",
    "htmlName": "t < 800 ms",
    "count": 16,
    "percentage": 48
},
    "group2": {
    "name": "800 ms <= t < 1200 ms",
    "htmlName": "t >= 800 ms <br> t < 1200 ms",
    "count": 3,
    "percentage": 9
},
    "group3": {
    "name": "t >= 1200 ms",
    "htmlName": "t >= 1200 ms",
    "count": 13,
    "percentage": 39
},
    "group4": {
    "name": "failed",
    "htmlName": "failed",
    "count": 1,
    "percentage": 3
},
    "meanNumberOfRequestsPerSecond": {
        "total": 0.25,
        "ok": 0.24242424242424243,
        "ko": 0.007575757575757576
    }
},
"contents": {
"group_xui-010-homepag-0e4d4": {
          "type": "GROUP",
"name": "XUI_010_Homepage",
"path": "XUI_010_Homepage",
"pathFormatted": "group_xui-010-homepag-0e4d4",
"stats": {
    "name": "XUI_010_Homepage",
    "numberOfRequests": {
        "total": 1,
        "ok": 1,
        "ko": 0
    },
    "minResponseTime": {
        "total": 27597,
        "ok": 27597,
        "ko": 0
    },
    "maxResponseTime": {
        "total": 27597,
        "ok": 27597,
        "ko": 0
    },
    "meanResponseTime": {
        "total": 27597,
        "ok": 27597,
        "ko": 0
    },
    "standardDeviation": {
        "total": 0,
        "ok": 0,
        "ko": 0
    },
    "percentiles1": {
        "total": 27597,
        "ok": 27597,
        "ko": 0
    },
    "percentiles2": {
        "total": 27597,
        "ok": 27597,
        "ko": 0
    },
    "percentiles3": {
        "total": 27597,
        "ok": 27597,
        "ko": 0
    },
    "percentiles4": {
        "total": 27597,
        "ok": 27597,
        "ko": 0
    },
    "group1": {
    "name": "t < 800 ms",
    "htmlName": "t < 800 ms",
    "count": 0,
    "percentage": 0
},
    "group2": {
    "name": "800 ms <= t < 1200 ms",
    "htmlName": "t >= 800 ms <br> t < 1200 ms",
    "count": 0,
    "percentage": 0
},
    "group3": {
    "name": "t >= 1200 ms",
    "htmlName": "t >= 1200 ms",
    "count": 1,
    "percentage": 100
},
    "group4": {
    "name": "failed",
    "htmlName": "failed",
    "count": 0,
    "percentage": 0
},
    "meanNumberOfRequestsPerSecond": {
        "total": 0.007575757575757576,
        "ok": 0.007575757575757576,
        "ko": 0
    }
},
"contents": {
"req_xui-010-005-hom-0514a": {
        "type": "REQUEST",
        "name": "XUI_010_005_Homepage",
"path": "XUI_010_Homepage / XUI_010_005_Homepage",
"pathFormatted": "req_xui-010-homepag-8dfbb",
"stats": {
    "name": "XUI_010_005_Homepage",
    "numberOfRequests": {
        "total": 1,
        "ok": 1,
        "ko": 0
    },
    "minResponseTime": {
        "total": 242,
        "ok": 242,
        "ko": 0
    },
    "maxResponseTime": {
        "total": 242,
        "ok": 242,
        "ko": 0
    },
    "meanResponseTime": {
        "total": 242,
        "ok": 242,
        "ko": 0
    },
    "standardDeviation": {
        "total": 0,
        "ok": 0,
        "ko": 0
    },
    "percentiles1": {
        "total": 242,
        "ok": 242,
        "ko": 0
    },
    "percentiles2": {
        "total": 242,
        "ok": 242,
        "ko": 0
    },
    "percentiles3": {
        "total": 242,
        "ok": 242,
        "ko": 0
    },
    "percentiles4": {
        "total": 242,
        "ok": 242,
        "ko": 0
    },
    "group1": {
    "name": "t < 800 ms",
    "htmlName": "t < 800 ms",
    "count": 1,
    "percentage": 100
},
    "group2": {
    "name": "800 ms <= t < 1200 ms",
    "htmlName": "t >= 800 ms <br> t < 1200 ms",
    "count": 0,
    "percentage": 0
},
    "group3": {
    "name": "t >= 1200 ms",
    "htmlName": "t >= 1200 ms",
    "count": 0,
    "percentage": 0
},
    "group4": {
    "name": "failed",
    "htmlName": "failed",
    "count": 0,
    "percentage": 0
},
    "meanNumberOfRequestsPerSecond": {
        "total": 0.007575757575757576,
        "ok": 0.007575757575757576,
        "ko": 0
    }
}
    },"req_xui-common-000--1485f": {
        "type": "REQUEST",
        "name": "XUI_Common_000_ConfigurationUI",
"path": "XUI_010_Homepage / XUI_Common_000_ConfigurationUI",
"pathFormatted": "req_xui-010-homepag-38a11",
"stats": {
    "name": "XUI_Common_000_ConfigurationUI",
    "numberOfRequests": {
        "total": 1,
        "ok": 1,
        "ko": 0
    },
    "minResponseTime": {
        "total": 117,
        "ok": 117,
        "ko": 0
    },
    "maxResponseTime": {
        "total": 117,
        "ok": 117,
        "ko": 0
    },
    "meanResponseTime": {
        "total": 117,
        "ok": 117,
        "ko": 0
    },
    "standardDeviation": {
        "total": 0,
        "ok": 0,
        "ko": 0
    },
    "percentiles1": {
        "total": 117,
        "ok": 117,
        "ko": 0
    },
    "percentiles2": {
        "total": 117,
        "ok": 117,
        "ko": 0
    },
    "percentiles3": {
        "total": 117,
        "ok": 117,
        "ko": 0
    },
    "percentiles4": {
        "total": 117,
        "ok": 117,
        "ko": 0
    },
    "group1": {
    "name": "t < 800 ms",
    "htmlName": "t < 800 ms",
    "count": 1,
    "percentage": 100
},
    "group2": {
    "name": "800 ms <= t < 1200 ms",
    "htmlName": "t >= 800 ms <br> t < 1200 ms",
    "count": 0,
    "percentage": 0
},
    "group3": {
    "name": "t >= 1200 ms",
    "htmlName": "t >= 1200 ms",
    "count": 0,
    "percentage": 0
},
    "group4": {
    "name": "failed",
    "htmlName": "failed",
    "count": 0,
    "percentage": 0
},
    "meanNumberOfRequestsPerSecond": {
        "total": 0.007575757575757576,
        "ok": 0.007575757575757576,
        "ko": 0
    }
}
    },"req_xui-common-000--e3df9": {
        "type": "REQUEST",
        "name": "XUI_Common_000_ConfigJson",
"path": "XUI_010_Homepage / XUI_Common_000_ConfigJson",
"pathFormatted": "req_xui-010-homepag-58b8f",
"stats": {
    "name": "XUI_Common_000_ConfigJson",
    "numberOfRequests": {
        "total": 1,
        "ok": 1,
        "ko": 0
    },
    "minResponseTime": {
        "total": 57,
        "ok": 57,
        "ko": 0
    },
    "maxResponseTime": {
        "total": 57,
        "ok": 57,
        "ko": 0
    },
    "meanResponseTime": {
        "total": 57,
        "ok": 57,
        "ko": 0
    },
    "standardDeviation": {
        "total": 0,
        "ok": 0,
        "ko": 0
    },
    "percentiles1": {
        "total": 57,
        "ok": 57,
        "ko": 0
    },
    "percentiles2": {
        "total": 57,
        "ok": 57,
        "ko": 0
    },
    "percentiles3": {
        "total": 57,
        "ok": 57,
        "ko": 0
    },
    "percentiles4": {
        "total": 57,
        "ok": 57,
        "ko": 0
    },
    "group1": {
    "name": "t < 800 ms",
    "htmlName": "t < 800 ms",
    "count": 1,
    "percentage": 100
},
    "group2": {
    "name": "800 ms <= t < 1200 ms",
    "htmlName": "t >= 800 ms <br> t < 1200 ms",
    "count": 0,
    "percentage": 0
},
    "group3": {
    "name": "t >= 1200 ms",
    "htmlName": "t >= 1200 ms",
    "count": 0,
    "percentage": 0
},
    "group4": {
    "name": "failed",
    "htmlName": "failed",
    "count": 0,
    "percentage": 0
},
    "meanNumberOfRequestsPerSecond": {
        "total": 0.007575757575757576,
        "ok": 0.007575757575757576,
        "ko": 0
    }
}
    },"req_xui-common-000--59ddb": {
        "type": "REQUEST",
        "name": "XUI_Common_000_TsAndCs",
"path": "XUI_010_Homepage / XUI_Common_000_TsAndCs",
"pathFormatted": "req_xui-010-homepag-611d6",
"stats": {
    "name": "XUI_Common_000_TsAndCs",
    "numberOfRequests": {
        "total": 1,
        "ok": 1,
        "ko": 0
    },
    "minResponseTime": {
        "total": 161,
        "ok": 161,
        "ko": 0
    },
    "maxResponseTime": {
        "total": 161,
        "ok": 161,
        "ko": 0
    },
    "meanResponseTime": {
        "total": 161,
        "ok": 161,
        "ko": 0
    },
    "standardDeviation": {
        "total": 0,
        "ok": 0,
        "ko": 0
    },
    "percentiles1": {
        "total": 161,
        "ok": 161,
        "ko": 0
    },
    "percentiles2": {
        "total": 161,
        "ok": 161,
        "ko": 0
    },
    "percentiles3": {
        "total": 161,
        "ok": 161,
        "ko": 0
    },
    "percentiles4": {
        "total": 161,
        "ok": 161,
        "ko": 0
    },
    "group1": {
    "name": "t < 800 ms",
    "htmlName": "t < 800 ms",
    "count": 1,
    "percentage": 100
},
    "group2": {
    "name": "800 ms <= t < 1200 ms",
    "htmlName": "t >= 800 ms <br> t < 1200 ms",
    "count": 0,
    "percentage": 0
},
    "group3": {
    "name": "t >= 1200 ms",
    "htmlName": "t >= 1200 ms",
    "count": 0,
    "percentage": 0
},
    "group4": {
    "name": "failed",
    "htmlName": "failed",
    "count": 0,
    "percentage": 0
},
    "meanNumberOfRequestsPerSecond": {
        "total": 0.007575757575757576,
        "ok": 0.007575757575757576,
        "ko": 0
    }
}
    },"req_xui-common-000--d9e65": {
        "type": "REQUEST",
        "name": "XUI_Common_000_ConfigUI",
"path": "XUI_010_Homepage / XUI_Common_000_ConfigUI",
"pathFormatted": "req_xui-010-homepag-48322",
"stats": {
    "name": "XUI_Common_000_ConfigUI",
    "numberOfRequests": {
        "total": 1,
        "ok": 1,
        "ko": 0
    },
    "minResponseTime": {
        "total": 108,
        "ok": 108,
        "ko": 0
    },
    "maxResponseTime": {
        "total": 108,
        "ok": 108,
        "ko": 0
    },
    "meanResponseTime": {
        "total": 108,
        "ok": 108,
        "ko": 0
    },
    "standardDeviation": {
        "total": 0,
        "ok": 0,
        "ko": 0
    },
    "percentiles1": {
        "total": 108,
        "ok": 108,
        "ko": 0
    },
    "percentiles2": {
        "total": 108,
        "ok": 108,
        "ko": 0
    },
    "percentiles3": {
        "total": 108,
        "ok": 108,
        "ko": 0
    },
    "percentiles4": {
        "total": 108,
        "ok": 108,
        "ko": 0
    },
    "group1": {
    "name": "t < 800 ms",
    "htmlName": "t < 800 ms",
    "count": 1,
    "percentage": 100
},
    "group2": {
    "name": "800 ms <= t < 1200 ms",
    "htmlName": "t >= 800 ms <br> t < 1200 ms",
    "count": 0,
    "percentage": 0
},
    "group3": {
    "name": "t >= 1200 ms",
    "htmlName": "t >= 1200 ms",
    "count": 0,
    "percentage": 0
},
    "group4": {
    "name": "failed",
    "htmlName": "failed",
    "count": 0,
    "percentage": 0
},
    "meanNumberOfRequestsPerSecond": {
        "total": 0.007575757575757576,
        "ok": 0.007575757575757576,
        "ko": 0
    }
}
    },"req_xui-common-000--ca7fe": {
        "type": "REQUEST",
        "name": "XUI_Common_000_UserDetails",
"path": "XUI_010_Homepage / XUI_Common_000_UserDetails",
"pathFormatted": "req_xui-010-homepag-398b0",
"stats": {
    "name": "XUI_Common_000_UserDetails",
    "numberOfRequests": {
        "total": 1,
        "ok": 1,
        "ko": 0
    },
    "minResponseTime": {
        "total": 68,
        "ok": 68,
        "ko": 0
    },
    "maxResponseTime": {
        "total": 68,
        "ok": 68,
        "ko": 0
    },
    "meanResponseTime": {
        "total": 68,
        "ok": 68,
        "ko": 0
    },
    "standardDeviation": {
        "total": 0,
        "ok": 0,
        "ko": 0
    },
    "percentiles1": {
        "total": 68,
        "ok": 68,
        "ko": 0
    },
    "percentiles2": {
        "total": 68,
        "ok": 68,
        "ko": 0
    },
    "percentiles3": {
        "total": 68,
        "ok": 68,
        "ko": 0
    },
    "percentiles4": {
        "total": 68,
        "ok": 68,
        "ko": 0
    },
    "group1": {
    "name": "t < 800 ms",
    "htmlName": "t < 800 ms",
    "count": 1,
    "percentage": 100
},
    "group2": {
    "name": "800 ms <= t < 1200 ms",
    "htmlName": "t >= 800 ms <br> t < 1200 ms",
    "count": 0,
    "percentage": 0
},
    "group3": {
    "name": "t >= 1200 ms",
    "htmlName": "t >= 1200 ms",
    "count": 0,
    "percentage": 0
},
    "group4": {
    "name": "failed",
    "htmlName": "failed",
    "count": 0,
    "percentage": 0
},
    "meanNumberOfRequestsPerSecond": {
        "total": 0.007575757575757576,
        "ok": 0.007575757575757576,
        "ko": 0
    }
}
    },"req_xui-common-000--2197b": {
        "type": "REQUEST",
        "name": "XUI_Common_000_IsAuthenticated",
"path": "XUI_010_Homepage / XUI_Common_000_IsAuthenticated",
"pathFormatted": "req_xui-010-homepag-181f7",
"stats": {
    "name": "XUI_Common_000_IsAuthenticated",
    "numberOfRequests": {
        "total": 1,
        "ok": 1,
        "ko": 0
    },
    "minResponseTime": {
        "total": 51,
        "ok": 51,
        "ko": 0
    },
    "maxResponseTime": {
        "total": 51,
        "ok": 51,
        "ko": 0
    },
    "meanResponseTime": {
        "total": 51,
        "ok": 51,
        "ko": 0
    },
    "standardDeviation": {
        "total": 0,
        "ok": 0,
        "ko": 0
    },
    "percentiles1": {
        "total": 51,
        "ok": 51,
        "ko": 0
    },
    "percentiles2": {
        "total": 51,
        "ok": 51,
        "ko": 0
    },
    "percentiles3": {
        "total": 51,
        "ok": 51,
        "ko": 0
    },
    "percentiles4": {
        "total": 51,
        "ok": 51,
        "ko": 0
    },
    "group1": {
    "name": "t < 800 ms",
    "htmlName": "t < 800 ms",
    "count": 1,
    "percentage": 100
},
    "group2": {
    "name": "800 ms <= t < 1200 ms",
    "htmlName": "t >= 800 ms <br> t < 1200 ms",
    "count": 0,
    "percentage": 0
},
    "group3": {
    "name": "t >= 1200 ms",
    "htmlName": "t >= 1200 ms",
    "count": 0,
    "percentage": 0
},
    "group4": {
    "name": "failed",
    "htmlName": "failed",
    "count": 0,
    "percentage": 0
},
    "meanNumberOfRequestsPerSecond": {
        "total": 0.007575757575757576,
        "ok": 0.007575757575757576,
        "ko": 0
    }
}
    },"req_xui-010-010-aut-50e55": {
        "type": "REQUEST",
        "name": "XUI_010_010_AuthLogin",
"path": "XUI_010_Homepage / XUI_010_010_AuthLogin",
"pathFormatted": "req_xui-010-homepag-156cd",
"stats": {
    "name": "XUI_010_010_AuthLogin",
    "numberOfRequests": {
        "total": 1,
        "ok": 1,
        "ko": 0
    },
    "minResponseTime": {
        "total": 51,
        "ok": 51,
        "ko": 0
    },
    "maxResponseTime": {
        "total": 51,
        "ok": 51,
        "ko": 0
    },
    "meanResponseTime": {
        "total": 51,
        "ok": 51,
        "ko": 0
    },
    "standardDeviation": {
        "total": 0,
        "ok": 0,
        "ko": 0
    },
    "percentiles1": {
        "total": 51,
        "ok": 51,
        "ko": 0
    },
    "percentiles2": {
        "total": 51,
        "ok": 51,
        "ko": 0
    },
    "percentiles3": {
        "total": 51,
        "ok": 51,
        "ko": 0
    },
    "percentiles4": {
        "total": 51,
        "ok": 51,
        "ko": 0
    },
    "group1": {
    "name": "t < 800 ms",
    "htmlName": "t < 800 ms",
    "count": 1,
    "percentage": 100
},
    "group2": {
    "name": "800 ms <= t < 1200 ms",
    "htmlName": "t >= 800 ms <br> t < 1200 ms",
    "count": 0,
    "percentage": 0
},
    "group3": {
    "name": "t >= 1200 ms",
    "htmlName": "t >= 1200 ms",
    "count": 0,
    "percentage": 0
},
    "group4": {
    "name": "failed",
    "htmlName": "failed",
    "count": 0,
    "percentage": 0
},
    "meanNumberOfRequestsPerSecond": {
        "total": 0.007575757575757576,
        "ok": 0.007575757575757576,
        "ko": 0
    }
}
    },"req_xui-010-010-aut-15a35": {
        "type": "REQUEST",
        "name": "XUI_010_010_AuthLogin Redirect 1",
"path": "XUI_010_Homepage / XUI_010_010_AuthLogin Redirect 1",
"pathFormatted": "req_xui-010-homepag-d3255",
"stats": {
    "name": "XUI_010_010_AuthLogin Redirect 1",
    "numberOfRequests": {
        "total": 1,
        "ok": 1,
        "ko": 0
    },
    "minResponseTime": {
        "total": 547,
        "ok": 547,
        "ko": 0
    },
    "maxResponseTime": {
        "total": 547,
        "ok": 547,
        "ko": 0
    },
    "meanResponseTime": {
        "total": 547,
        "ok": 547,
        "ko": 0
    },
    "standardDeviation": {
        "total": 0,
        "ok": 0,
        "ko": 0
    },
    "percentiles1": {
        "total": 547,
        "ok": 547,
        "ko": 0
    },
    "percentiles2": {
        "total": 547,
        "ok": 547,
        "ko": 0
    },
    "percentiles3": {
        "total": 547,
        "ok": 547,
        "ko": 0
    },
    "percentiles4": {
        "total": 547,
        "ok": 547,
        "ko": 0
    },
    "group1": {
    "name": "t < 800 ms",
    "htmlName": "t < 800 ms",
    "count": 1,
    "percentage": 100
},
    "group2": {
    "name": "800 ms <= t < 1200 ms",
    "htmlName": "t >= 800 ms <br> t < 1200 ms",
    "count": 0,
    "percentage": 0
},
    "group3": {
    "name": "t >= 1200 ms",
    "htmlName": "t >= 1200 ms",
    "count": 0,
    "percentage": 0
},
    "group4": {
    "name": "failed",
    "htmlName": "failed",
    "count": 0,
    "percentage": 0
},
    "meanNumberOfRequestsPerSecond": {
        "total": 0.007575757575757576,
        "ok": 0.007575757575757576,
        "ko": 0
    }
}
    },"req_xui-010-010-aut-b4f20": {
        "type": "REQUEST",
        "name": "XUI_010_010_AuthLogin Redirect 2",
"path": "XUI_010_Homepage / XUI_010_010_AuthLogin Redirect 2",
"pathFormatted": "req_xui-010-homepag-09741",
"stats": {
    "name": "XUI_010_010_AuthLogin Redirect 2",
    "numberOfRequests": {
        "total": 1,
        "ok": 1,
        "ko": 0
    },
    "minResponseTime": {
        "total": 209,
        "ok": 209,
        "ko": 0
    },
    "maxResponseTime": {
        "total": 209,
        "ok": 209,
        "ko": 0
    },
    "meanResponseTime": {
        "total": 209,
        "ok": 209,
        "ko": 0
    },
    "standardDeviation": {
        "total": 0,
        "ok": 0,
        "ko": 0
    },
    "percentiles1": {
        "total": 209,
        "ok": 209,
        "ko": 0
    },
    "percentiles2": {
        "total": 209,
        "ok": 209,
        "ko": 0
    },
    "percentiles3": {
        "total": 209,
        "ok": 209,
        "ko": 0
    },
    "percentiles4": {
        "total": 209,
        "ok": 209,
        "ko": 0
    },
    "group1": {
    "name": "t < 800 ms",
    "htmlName": "t < 800 ms",
    "count": 1,
    "percentage": 100
},
    "group2": {
    "name": "800 ms <= t < 1200 ms",
    "htmlName": "t >= 800 ms <br> t < 1200 ms",
    "count": 0,
    "percentage": 0
},
    "group3": {
    "name": "t >= 1200 ms",
    "htmlName": "t >= 1200 ms",
    "count": 0,
    "percentage": 0
},
    "group4": {
    "name": "failed",
    "htmlName": "failed",
    "count": 0,
    "percentage": 0
},
    "meanNumberOfRequestsPerSecond": {
        "total": 0.007575757575757576,
        "ok": 0.007575757575757576,
        "ko": 0
    }
}
    }
}

     },"group_xui-020-login-947c6": {
          "type": "GROUP",
"name": "XUI_020_Login",
"path": "XUI_020_Login",
"pathFormatted": "group_xui-020-login-947c6",
"stats": {
    "name": "XUI_020_Login",
    "numberOfRequests": {
        "total": 1,
        "ok": 1,
        "ko": 0
    },
    "minResponseTime": {
        "total": 25333,
        "ok": 25333,
        "ko": 0
    },
    "maxResponseTime": {
        "total": 25333,
        "ok": 25333,
        "ko": 0
    },
    "meanResponseTime": {
        "total": 25333,
        "ok": 25333,
        "ko": 0
    },
    "standardDeviation": {
        "total": 0,
        "ok": 0,
        "ko": 0
    },
    "percentiles1": {
        "total": 25333,
        "ok": 25333,
        "ko": 0
    },
    "percentiles2": {
        "total": 25333,
        "ok": 25333,
        "ko": 0
    },
    "percentiles3": {
        "total": 25333,
        "ok": 25333,
        "ko": 0
    },
    "percentiles4": {
        "total": 25333,
        "ok": 25333,
        "ko": 0
    },
    "group1": {
    "name": "t < 800 ms",
    "htmlName": "t < 800 ms",
    "count": 0,
    "percentage": 0
},
    "group2": {
    "name": "800 ms <= t < 1200 ms",
    "htmlName": "t >= 800 ms <br> t < 1200 ms",
    "count": 0,
    "percentage": 0
},
    "group3": {
    "name": "t >= 1200 ms",
    "htmlName": "t >= 1200 ms",
    "count": 1,
    "percentage": 100
},
    "group4": {
    "name": "failed",
    "htmlName": "failed",
    "count": 0,
    "percentage": 0
},
    "meanNumberOfRequestsPerSecond": {
        "total": 0.007575757575757576,
        "ok": 0.007575757575757576,
        "ko": 0
    }
},
"contents": {
"req_xui-020-005-log-4232d": {
        "type": "REQUEST",
        "name": "XUI_020_005_Login",
"path": "XUI_020_Login / XUI_020_005_Login",
"pathFormatted": "req_xui-020-login---9a839",
"stats": {
    "name": "XUI_020_005_Login",
    "numberOfRequests": {
        "total": 1,
        "ok": 1,
        "ko": 0
    },
    "minResponseTime": {
        "total": 894,
        "ok": 894,
        "ko": 0
    },
    "maxResponseTime": {
        "total": 894,
        "ok": 894,
        "ko": 0
    },
    "meanResponseTime": {
        "total": 894,
        "ok": 894,
        "ko": 0
    },
    "standardDeviation": {
        "total": 0,
        "ok": 0,
        "ko": 0
    },
    "percentiles1": {
        "total": 894,
        "ok": 894,
        "ko": 0
    },
    "percentiles2": {
        "total": 894,
        "ok": 894,
        "ko": 0
    },
    "percentiles3": {
        "total": 894,
        "ok": 894,
        "ko": 0
    },
    "percentiles4": {
        "total": 894,
        "ok": 894,
        "ko": 0
    },
    "group1": {
    "name": "t < 800 ms",
    "htmlName": "t < 800 ms",
    "count": 0,
    "percentage": 0
},
    "group2": {
    "name": "800 ms <= t < 1200 ms",
    "htmlName": "t >= 800 ms <br> t < 1200 ms",
    "count": 1,
    "percentage": 100
},
    "group3": {
    "name": "t >= 1200 ms",
    "htmlName": "t >= 1200 ms",
    "count": 0,
    "percentage": 0
},
    "group4": {
    "name": "failed",
    "htmlName": "failed",
    "count": 0,
    "percentage": 0
},
    "meanNumberOfRequestsPerSecond": {
        "total": 0.007575757575757576,
        "ok": 0.007575757575757576,
        "ko": 0
    }
}
    },"req_xui-020-005-log-cc8b9": {
        "type": "REQUEST",
        "name": "XUI_020_005_Login Redirect 1",
"path": "XUI_020_Login / XUI_020_005_Login Redirect 1",
"pathFormatted": "req_xui-020-login---1be0c",
"stats": {
    "name": "XUI_020_005_Login Redirect 1",
    "numberOfRequests": {
        "total": 1,
        "ok": 1,
        "ko": 0
    },
    "minResponseTime": {
        "total": 2526,
        "ok": 2526,
        "ko": 0
    },
    "maxResponseTime": {
        "total": 2526,
        "ok": 2526,
        "ko": 0
    },
    "meanResponseTime": {
        "total": 2526,
        "ok": 2526,
        "ko": 0
    },
    "standardDeviation": {
        "total": 0,
        "ok": 0,
        "ko": 0
    },
    "percentiles1": {
        "total": 2526,
        "ok": 2526,
        "ko": 0
    },
    "percentiles2": {
        "total": 2526,
        "ok": 2526,
        "ko": 0
    },
    "percentiles3": {
        "total": 2526,
        "ok": 2526,
        "ko": 0
    },
    "percentiles4": {
        "total": 2526,
        "ok": 2526,
        "ko": 0
    },
    "group1": {
    "name": "t < 800 ms",
    "htmlName": "t < 800 ms",
    "count": 0,
    "percentage": 0
},
    "group2": {
    "name": "800 ms <= t < 1200 ms",
    "htmlName": "t >= 800 ms <br> t < 1200 ms",
    "count": 0,
    "percentage": 0
},
    "group3": {
    "name": "t >= 1200 ms",
    "htmlName": "t >= 1200 ms",
    "count": 1,
    "percentage": 100
},
    "group4": {
    "name": "failed",
    "htmlName": "failed",
    "count": 0,
    "percentage": 0
},
    "meanNumberOfRequestsPerSecond": {
        "total": 0.007575757575757576,
        "ok": 0.007575757575757576,
        "ko": 0
    }
}
    },"req_xui-020-005-log-68faf": {
        "type": "REQUEST",
        "name": "XUI_020_005_Login Redirect 2",
"path": "XUI_020_Login / XUI_020_005_Login Redirect 2",
"pathFormatted": "req_xui-020-login---97692",
"stats": {
    "name": "XUI_020_005_Login Redirect 2",
    "numberOfRequests": {
        "total": 1,
        "ok": 1,
        "ko": 0
    },
    "minResponseTime": {
        "total": 151,
        "ok": 151,
        "ko": 0
    },
    "maxResponseTime": {
        "total": 151,
        "ok": 151,
        "ko": 0
    },
    "meanResponseTime": {
        "total": 151,
        "ok": 151,
        "ko": 0
    },
    "standardDeviation": {
        "total": 0,
        "ok": 0,
        "ko": 0
    },
    "percentiles1": {
        "total": 151,
        "ok": 151,
        "ko": 0
    },
    "percentiles2": {
        "total": 151,
        "ok": 151,
        "ko": 0
    },
    "percentiles3": {
        "total": 151,
        "ok": 151,
        "ko": 0
    },
    "percentiles4": {
        "total": 151,
        "ok": 151,
        "ko": 0
    },
    "group1": {
    "name": "t < 800 ms",
    "htmlName": "t < 800 ms",
    "count": 1,
    "percentage": 100
},
    "group2": {
    "name": "800 ms <= t < 1200 ms",
    "htmlName": "t >= 800 ms <br> t < 1200 ms",
    "count": 0,
    "percentage": 0
},
    "group3": {
    "name": "t >= 1200 ms",
    "htmlName": "t >= 1200 ms",
    "count": 0,
    "percentage": 0
},
    "group4": {
    "name": "failed",
    "htmlName": "failed",
    "count": 0,
    "percentage": 0
},
    "meanNumberOfRequestsPerSecond": {
        "total": 0.007575757575757576,
        "ok": 0.007575757575757576,
        "ko": 0
    }
}
    },"req_xui-common-000--1485f": {
        "type": "REQUEST",
        "name": "XUI_Common_000_ConfigurationUI",
"path": "XUI_020_Login / XUI_Common_000_ConfigurationUI",
"pathFormatted": "req_xui-020-login---6e0d2",
"stats": {
    "name": "XUI_Common_000_ConfigurationUI",
    "numberOfRequests": {
        "total": 1,
        "ok": 1,
        "ko": 0
    },
    "minResponseTime": {
        "total": 89,
        "ok": 89,
        "ko": 0
    },
    "maxResponseTime": {
        "total": 89,
        "ok": 89,
        "ko": 0
    },
    "meanResponseTime": {
        "total": 89,
        "ok": 89,
        "ko": 0
    },
    "standardDeviation": {
        "total": 0,
        "ok": 0,
        "ko": 0
    },
    "percentiles1": {
        "total": 89,
        "ok": 89,
        "ko": 0
    },
    "percentiles2": {
        "total": 89,
        "ok": 89,
        "ko": 0
    },
    "percentiles3": {
        "total": 89,
        "ok": 89,
        "ko": 0
    },
    "percentiles4": {
        "total": 89,
        "ok": 89,
        "ko": 0
    },
    "group1": {
    "name": "t < 800 ms",
    "htmlName": "t < 800 ms",
    "count": 1,
    "percentage": 100
},
    "group2": {
    "name": "800 ms <= t < 1200 ms",
    "htmlName": "t >= 800 ms <br> t < 1200 ms",
    "count": 0,
    "percentage": 0
},
    "group3": {
    "name": "t >= 1200 ms",
    "htmlName": "t >= 1200 ms",
    "count": 0,
    "percentage": 0
},
    "group4": {
    "name": "failed",
    "htmlName": "failed",
    "count": 0,
    "percentage": 0
},
    "meanNumberOfRequestsPerSecond": {
        "total": 0.007575757575757576,
        "ok": 0.007575757575757576,
        "ko": 0
    }
}
    },"req_xui-common-000--e3df9": {
        "type": "REQUEST",
        "name": "XUI_Common_000_ConfigJson",
"path": "XUI_020_Login / XUI_Common_000_ConfigJson",
"pathFormatted": "req_xui-020-login---29323",
"stats": {
    "name": "XUI_Common_000_ConfigJson",
    "numberOfRequests": {
        "total": 1,
        "ok": 1,
        "ko": 0
    },
    "minResponseTime": {
        "total": 29,
        "ok": 29,
        "ko": 0
    },
    "maxResponseTime": {
        "total": 29,
        "ok": 29,
        "ko": 0
    },
    "meanResponseTime": {
        "total": 29,
        "ok": 29,
        "ko": 0
    },
    "standardDeviation": {
        "total": 0,
        "ok": 0,
        "ko": 0
    },
    "percentiles1": {
        "total": 29,
        "ok": 29,
        "ko": 0
    },
    "percentiles2": {
        "total": 29,
        "ok": 29,
        "ko": 0
    },
    "percentiles3": {
        "total": 29,
        "ok": 29,
        "ko": 0
    },
    "percentiles4": {
        "total": 29,
        "ok": 29,
        "ko": 0
    },
    "group1": {
    "name": "t < 800 ms",
    "htmlName": "t < 800 ms",
    "count": 1,
    "percentage": 100
},
    "group2": {
    "name": "800 ms <= t < 1200 ms",
    "htmlName": "t >= 800 ms <br> t < 1200 ms",
    "count": 0,
    "percentage": 0
},
    "group3": {
    "name": "t >= 1200 ms",
    "htmlName": "t >= 1200 ms",
    "count": 0,
    "percentage": 0
},
    "group4": {
    "name": "failed",
    "htmlName": "failed",
    "count": 0,
    "percentage": 0
},
    "meanNumberOfRequestsPerSecond": {
        "total": 0.007575757575757576,
        "ok": 0.007575757575757576,
        "ko": 0
    }
}
    },"req_xui-common-000--59ddb": {
        "type": "REQUEST",
        "name": "XUI_Common_000_TsAndCs",
"path": "XUI_020_Login / XUI_Common_000_TsAndCs",
"pathFormatted": "req_xui-020-login---0808c",
"stats": {
    "name": "XUI_Common_000_TsAndCs",
    "numberOfRequests": {
        "total": 1,
        "ok": 1,
        "ko": 0
    },
    "minResponseTime": {
        "total": 66,
        "ok": 66,
        "ko": 0
    },
    "maxResponseTime": {
        "total": 66,
        "ok": 66,
        "ko": 0
    },
    "meanResponseTime": {
        "total": 66,
        "ok": 66,
        "ko": 0
    },
    "standardDeviation": {
        "total": 0,
        "ok": 0,
        "ko": 0
    },
    "percentiles1": {
        "total": 66,
        "ok": 66,
        "ko": 0
    },
    "percentiles2": {
        "total": 66,
        "ok": 66,
        "ko": 0
    },
    "percentiles3": {
        "total": 66,
        "ok": 66,
        "ko": 0
    },
    "percentiles4": {
        "total": 66,
        "ok": 66,
        "ko": 0
    },
    "group1": {
    "name": "t < 800 ms",
    "htmlName": "t < 800 ms",
    "count": 1,
    "percentage": 100
},
    "group2": {
    "name": "800 ms <= t < 1200 ms",
    "htmlName": "t >= 800 ms <br> t < 1200 ms",
    "count": 0,
    "percentage": 0
},
    "group3": {
    "name": "t >= 1200 ms",
    "htmlName": "t >= 1200 ms",
    "count": 0,
    "percentage": 0
},
    "group4": {
    "name": "failed",
    "htmlName": "failed",
    "count": 0,
    "percentage": 0
},
    "meanNumberOfRequestsPerSecond": {
        "total": 0.007575757575757576,
        "ok": 0.007575757575757576,
        "ko": 0
    }
}
    },"req_xui-common-000--d9e65": {
        "type": "REQUEST",
        "name": "XUI_Common_000_ConfigUI",
"path": "XUI_020_Login / XUI_Common_000_ConfigUI",
"pathFormatted": "req_xui-020-login---7f694",
"stats": {
    "name": "XUI_Common_000_ConfigUI",
    "numberOfRequests": {
        "total": 1,
        "ok": 1,
        "ko": 0
    },
    "minResponseTime": {
        "total": 903,
        "ok": 903,
        "ko": 0
    },
    "maxResponseTime": {
        "total": 903,
        "ok": 903,
        "ko": 0
    },
    "meanResponseTime": {
        "total": 903,
        "ok": 903,
        "ko": 0
    },
    "standardDeviation": {
        "total": 0,
        "ok": 0,
        "ko": 0
    },
    "percentiles1": {
        "total": 903,
        "ok": 903,
        "ko": 0
    },
    "percentiles2": {
        "total": 903,
        "ok": 903,
        "ko": 0
    },
    "percentiles3": {
        "total": 903,
        "ok": 903,
        "ko": 0
    },
    "percentiles4": {
        "total": 903,
        "ok": 903,
        "ko": 0
    },
    "group1": {
    "name": "t < 800 ms",
    "htmlName": "t < 800 ms",
    "count": 0,
    "percentage": 0
},
    "group2": {
    "name": "800 ms <= t < 1200 ms",
    "htmlName": "t >= 800 ms <br> t < 1200 ms",
    "count": 1,
    "percentage": 100
},
    "group3": {
    "name": "t >= 1200 ms",
    "htmlName": "t >= 1200 ms",
    "count": 0,
    "percentage": 0
},
    "group4": {
    "name": "failed",
    "htmlName": "failed",
    "count": 0,
    "percentage": 0
},
    "meanNumberOfRequestsPerSecond": {
        "total": 0.007575757575757576,
        "ok": 0.007575757575757576,
        "ko": 0
    }
}
    },"req_xui-common-000--ca7fe": {
        "type": "REQUEST",
        "name": "XUI_Common_000_UserDetails",
"path": "XUI_020_Login / XUI_Common_000_UserDetails",
"pathFormatted": "req_xui-020-login---4f024",
"stats": {
    "name": "XUI_Common_000_UserDetails",
    "numberOfRequests": {
        "total": 1,
        "ok": 1,
        "ko": 0
    },
    "minResponseTime": {
        "total": 1475,
        "ok": 1475,
        "ko": 0
    },
    "maxResponseTime": {
        "total": 1475,
        "ok": 1475,
        "ko": 0
    },
    "meanResponseTime": {
        "total": 1475,
        "ok": 1475,
        "ko": 0
    },
    "standardDeviation": {
        "total": 0,
        "ok": 0,
        "ko": 0
    },
    "percentiles1": {
        "total": 1475,
        "ok": 1475,
        "ko": 0
    },
    "percentiles2": {
        "total": 1475,
        "ok": 1475,
        "ko": 0
    },
    "percentiles3": {
        "total": 1475,
        "ok": 1475,
        "ko": 0
    },
    "percentiles4": {
        "total": 1475,
        "ok": 1475,
        "ko": 0
    },
    "group1": {
    "name": "t < 800 ms",
    "htmlName": "t < 800 ms",
    "count": 0,
    "percentage": 0
},
    "group2": {
    "name": "800 ms <= t < 1200 ms",
    "htmlName": "t >= 800 ms <br> t < 1200 ms",
    "count": 0,
    "percentage": 0
},
    "group3": {
    "name": "t >= 1200 ms",
    "htmlName": "t >= 1200 ms",
    "count": 1,
    "percentage": 100
},
    "group4": {
    "name": "failed",
    "htmlName": "failed",
    "count": 0,
    "percentage": 0
},
    "meanNumberOfRequestsPerSecond": {
        "total": 0.007575757575757576,
        "ok": 0.007575757575757576,
        "ko": 0
    }
}
    },"req_xui-common-000--2197b": {
        "type": "REQUEST",
        "name": "XUI_Common_000_IsAuthenticated",
"path": "XUI_020_Login / XUI_Common_000_IsAuthenticated",
"pathFormatted": "req_xui-020-login---751a7",
"stats": {
    "name": "XUI_Common_000_IsAuthenticated",
    "numberOfRequests": {
        "total": 1,
        "ok": 1,
        "ko": 0
    },
    "minResponseTime": {
        "total": 549,
        "ok": 549,
        "ko": 0
    },
    "maxResponseTime": {
        "total": 549,
        "ok": 549,
        "ko": 0
    },
    "meanResponseTime": {
        "total": 549,
        "ok": 549,
        "ko": 0
    },
    "standardDeviation": {
        "total": 0,
        "ok": 0,
        "ko": 0
    },
    "percentiles1": {
        "total": 549,
        "ok": 549,
        "ko": 0
    },
    "percentiles2": {
        "total": 549,
        "ok": 549,
        "ko": 0
    },
    "percentiles3": {
        "total": 549,
        "ok": 549,
        "ko": 0
    },
    "percentiles4": {
        "total": 549,
        "ok": 549,
        "ko": 0
    },
    "group1": {
    "name": "t < 800 ms",
    "htmlName": "t < 800 ms",
    "count": 1,
    "percentage": 100
},
    "group2": {
    "name": "800 ms <= t < 1200 ms",
    "htmlName": "t >= 800 ms <br> t < 1200 ms",
    "count": 0,
    "percentage": 0
},
    "group3": {
    "name": "t >= 1200 ms",
    "htmlName": "t >= 1200 ms",
    "count": 0,
    "percentage": 0
},
    "group4": {
    "name": "failed",
    "htmlName": "failed",
    "count": 0,
    "percentage": 0
},
    "meanNumberOfRequestsPerSecond": {
        "total": 0.007575757575757576,
        "ok": 0.007575757575757576,
        "ko": 0
    }
}
    },"req_xui-common-000--0918f": {
        "type": "REQUEST",
        "name": "XUI_Common_000_MonitoringTools",
"path": "XUI_020_Login / XUI_Common_000_MonitoringTools",
"pathFormatted": "req_xui-020-login---45021",
"stats": {
    "name": "XUI_Common_000_MonitoringTools",
    "numberOfRequests": {
        "total": 1,
        "ok": 1,
        "ko": 0
    },
    "minResponseTime": {
        "total": 323,
        "ok": 323,
        "ko": 0
    },
    "maxResponseTime": {
        "total": 323,
        "ok": 323,
        "ko": 0
    },
    "meanResponseTime": {
        "total": 323,
        "ok": 323,
        "ko": 0
    },
    "standardDeviation": {
        "total": 0,
        "ok": 0,
        "ko": 0
    },
    "percentiles1": {
        "total": 323,
        "ok": 323,
        "ko": 0
    },
    "percentiles2": {
        "total": 323,
        "ok": 323,
        "ko": 0
    },
    "percentiles3": {
        "total": 323,
        "ok": 323,
        "ko": 0
    },
    "percentiles4": {
        "total": 323,
        "ok": 323,
        "ko": 0
    },
    "group1": {
    "name": "t < 800 ms",
    "htmlName": "t < 800 ms",
    "count": 1,
    "percentage": 100
},
    "group2": {
    "name": "800 ms <= t < 1200 ms",
    "htmlName": "t >= 800 ms <br> t < 1200 ms",
    "count": 0,
    "percentage": 0
},
    "group3": {
    "name": "t >= 1200 ms",
    "htmlName": "t >= 1200 ms",
    "count": 0,
    "percentage": 0
},
    "group4": {
    "name": "failed",
    "htmlName": "failed",
    "count": 0,
    "percentage": 0
},
    "meanNumberOfRequestsPerSecond": {
        "total": 0.007575757575757576,
        "ok": 0.007575757575757576,
        "ko": 0
    }
}
    }
}

     },"group_xui-prl-030-cre-bca3e": {
          "type": "GROUP",
"name": "XUI_PRL_030_CreateCaseStart",
"path": "XUI_PRL_030_CreateCaseStart",
"pathFormatted": "group_xui-prl-030-cre-bca3e",
"stats": {
    "name": "XUI_PRL_030_CreateCaseStart",
    "numberOfRequests": {
        "total": 1,
        "ok": 1,
        "ko": 0
    },
    "minResponseTime": {
        "total": 3081,
        "ok": 3081,
        "ko": 0
    },
    "maxResponseTime": {
        "total": 3081,
        "ok": 3081,
        "ko": 0
    },
    "meanResponseTime": {
        "total": 3081,
        "ok": 3081,
        "ko": 0
    },
    "standardDeviation": {
        "total": 0,
        "ok": 0,
        "ko": 0
    },
    "percentiles1": {
        "total": 3081,
        "ok": 3081,
        "ko": 0
    },
    "percentiles2": {
        "total": 3081,
        "ok": 3081,
        "ko": 0
    },
    "percentiles3": {
        "total": 3081,
        "ok": 3081,
        "ko": 0
    },
    "percentiles4": {
        "total": 3081,
        "ok": 3081,
        "ko": 0
    },
    "group1": {
    "name": "t < 800 ms",
    "htmlName": "t < 800 ms",
    "count": 0,
    "percentage": 0
},
    "group2": {
    "name": "800 ms <= t < 1200 ms",
    "htmlName": "t >= 800 ms <br> t < 1200 ms",
    "count": 0,
    "percentage": 0
},
    "group3": {
    "name": "t >= 1200 ms",
    "htmlName": "t >= 1200 ms",
    "count": 1,
    "percentage": 100
},
    "group4": {
    "name": "failed",
    "htmlName": "failed",
    "count": 0,
    "percentage": 0
},
    "meanNumberOfRequestsPerSecond": {
        "total": 0.007575757575757576,
        "ok": 0.007575757575757576,
        "ko": 0
    }
},
"contents": {
"req_xui-prl-030-005-dc4bc": {
        "type": "REQUEST",
        "name": "XUI_PRL_030_005_CreateCaseStart",
"path": "XUI_PRL_030_CreateCaseStart / XUI_PRL_030_005_CreateCaseStart",
"pathFormatted": "req_xui-prl-030-cre-dbfa5",
"stats": {
    "name": "XUI_PRL_030_005_CreateCaseStart",
    "numberOfRequests": {
        "total": 1,
        "ok": 1,
        "ko": 0
    },
    "minResponseTime": {
        "total": 3081,
        "ok": 3081,
        "ko": 0
    },
    "maxResponseTime": {
        "total": 3081,
        "ok": 3081,
        "ko": 0
    },
    "meanResponseTime": {
        "total": 3081,
        "ok": 3081,
        "ko": 0
    },
    "standardDeviation": {
        "total": 0,
        "ok": 0,
        "ko": 0
    },
    "percentiles1": {
        "total": 3081,
        "ok": 3081,
        "ko": 0
    },
    "percentiles2": {
        "total": 3081,
        "ok": 3081,
        "ko": 0
    },
    "percentiles3": {
        "total": 3081,
        "ok": 3081,
        "ko": 0
    },
    "percentiles4": {
        "total": 3081,
        "ok": 3081,
        "ko": 0
    },
    "group1": {
    "name": "t < 800 ms",
    "htmlName": "t < 800 ms",
    "count": 0,
    "percentage": 0
},
    "group2": {
    "name": "800 ms <= t < 1200 ms",
    "htmlName": "t >= 800 ms <br> t < 1200 ms",
    "count": 0,
    "percentage": 0
},
    "group3": {
    "name": "t >= 1200 ms",
    "htmlName": "t >= 1200 ms",
    "count": 1,
    "percentage": 100
},
    "group4": {
    "name": "failed",
    "htmlName": "failed",
    "count": 0,
    "percentage": 0
},
    "meanNumberOfRequestsPerSecond": {
        "total": 0.007575757575757576,
        "ok": 0.007575757575757576,
        "ko": 0
    }
}
    }
}

     },"group_xui-prl-031-typ-6f37b": {
          "type": "GROUP",
"name": "XUI_PRL_031_Type_Of_Application",
"path": "XUI_PRL_031_Type_Of_Application",
"pathFormatted": "group_xui-prl-031-typ-6f37b",
"stats": {
    "name": "XUI_PRL_031_Type_Of_Application",
    "numberOfRequests": {
        "total": 1,
        "ok": 1,
        "ko": 0
    },
    "minResponseTime": {
        "total": 2833,
        "ok": 2833,
        "ko": 0
    },
    "maxResponseTime": {
        "total": 2833,
        "ok": 2833,
        "ko": 0
    },
    "meanResponseTime": {
        "total": 2833,
        "ok": 2833,
        "ko": 0
    },
    "standardDeviation": {
        "total": 0,
        "ok": 0,
        "ko": 0
    },
    "percentiles1": {
        "total": 2833,
        "ok": 2833,
        "ko": 0
    },
    "percentiles2": {
        "total": 2833,
        "ok": 2833,
        "ko": 0
    },
    "percentiles3": {
        "total": 2833,
        "ok": 2833,
        "ko": 0
    },
    "percentiles4": {
        "total": 2833,
        "ok": 2833,
        "ko": 0
    },
    "group1": {
    "name": "t < 800 ms",
    "htmlName": "t < 800 ms",
    "count": 0,
    "percentage": 0
},
    "group2": {
    "name": "800 ms <= t < 1200 ms",
    "htmlName": "t >= 800 ms <br> t < 1200 ms",
    "count": 0,
    "percentage": 0
},
    "group3": {
    "name": "t >= 1200 ms",
    "htmlName": "t >= 1200 ms",
    "count": 1,
    "percentage": 100
},
    "group4": {
    "name": "failed",
    "htmlName": "failed",
    "count": 0,
    "percentage": 0
},
    "meanNumberOfRequestsPerSecond": {
        "total": 0.007575757575757576,
        "ok": 0.007575757575757576,
        "ko": 0
    }
},
"contents": {
"req_xui-prl-031-005-9bd4e": {
        "type": "REQUEST",
        "name": "XUI_PRL_031_005_Type_Of_Application",
"path": "XUI_PRL_031_Type_Of_Application / XUI_PRL_031_005_Type_Of_Application",
"pathFormatted": "req_xui-prl-031-typ-9fa46",
"stats": {
    "name": "XUI_PRL_031_005_Type_Of_Application",
    "numberOfRequests": {
        "total": 1,
        "ok": 1,
        "ko": 0
    },
    "minResponseTime": {
        "total": 2833,
        "ok": 2833,
        "ko": 0
    },
    "maxResponseTime": {
        "total": 2833,
        "ok": 2833,
        "ko": 0
    },
    "meanResponseTime": {
        "total": 2833,
        "ok": 2833,
        "ko": 0
    },
    "standardDeviation": {
        "total": 0,
        "ok": 0,
        "ko": 0
    },
    "percentiles1": {
        "total": 2833,
        "ok": 2833,
        "ko": 0
    },
    "percentiles2": {
        "total": 2833,
        "ok": 2833,
        "ko": 0
    },
    "percentiles3": {
        "total": 2833,
        "ok": 2833,
        "ko": 0
    },
    "percentiles4": {
        "total": 2833,
        "ok": 2833,
        "ko": 0
    },
    "group1": {
    "name": "t < 800 ms",
    "htmlName": "t < 800 ms",
    "count": 0,
    "percentage": 0
},
    "group2": {
    "name": "800 ms <= t < 1200 ms",
    "htmlName": "t >= 800 ms <br> t < 1200 ms",
    "count": 0,
    "percentage": 0
},
    "group3": {
    "name": "t >= 1200 ms",
    "htmlName": "t >= 1200 ms",
    "count": 1,
    "percentage": 100
},
    "group4": {
    "name": "failed",
    "htmlName": "failed",
    "count": 0,
    "percentage": 0
},
    "meanNumberOfRequestsPerSecond": {
        "total": 0.007575757575757576,
        "ok": 0.007575757575757576,
        "ko": 0
    }
}
    }
}

     },"group_xui-prl-032-app-4cd5d": {
          "type": "GROUP",
"name": "XUI_PRL_032_ApplicationCheckYourAnswers",
"path": "XUI_PRL_032_ApplicationCheckYourAnswers",
"pathFormatted": "group_xui-prl-032-app-4cd5d",
"stats": {
    "name": "XUI_PRL_032_ApplicationCheckYourAnswers",
    "numberOfRequests": {
        "total": 1,
        "ok": 1,
        "ko": 0
    },
    "minResponseTime": {
        "total": 17909,
        "ok": 17909,
        "ko": 0
    },
    "maxResponseTime": {
        "total": 17909,
        "ok": 17909,
        "ko": 0
    },
    "meanResponseTime": {
        "total": 17909,
        "ok": 17909,
        "ko": 0
    },
    "standardDeviation": {
        "total": 0,
        "ok": 0,
        "ko": 0
    },
    "percentiles1": {
        "total": 17909,
        "ok": 17909,
        "ko": 0
    },
    "percentiles2": {
        "total": 17909,
        "ok": 17909,
        "ko": 0
    },
    "percentiles3": {
        "total": 17909,
        "ok": 17909,
        "ko": 0
    },
    "percentiles4": {
        "total": 17909,
        "ok": 17909,
        "ko": 0
    },
    "group1": {
    "name": "t < 800 ms",
    "htmlName": "t < 800 ms",
    "count": 0,
    "percentage": 0
},
    "group2": {
    "name": "800 ms <= t < 1200 ms",
    "htmlName": "t >= 800 ms <br> t < 1200 ms",
    "count": 0,
    "percentage": 0
},
    "group3": {
    "name": "t >= 1200 ms",
    "htmlName": "t >= 1200 ms",
    "count": 1,
    "percentage": 100
},
    "group4": {
    "name": "failed",
    "htmlName": "failed",
    "count": 0,
    "percentage": 0
},
    "meanNumberOfRequestsPerSecond": {
        "total": 0.007575757575757576,
        "ok": 0.007575757575757576,
        "ko": 0
    }
},
"contents": {
"req_xui-prl-032-005-a94ab": {
        "type": "REQUEST",
        "name": "XUI_PRL_032_005_ApplicationCheckYourAnswers",
"path": "XUI_PRL_032_ApplicationCheckYourAnswers / XUI_PRL_032_005_ApplicationCheckYourAnswers",
"pathFormatted": "req_xui-prl-032-app-a865c",
"stats": {
    "name": "XUI_PRL_032_005_ApplicationCheckYourAnswers",
    "numberOfRequests": {
        "total": 1,
        "ok": 1,
        "ko": 0
    },
    "minResponseTime": {
        "total": 17909,
        "ok": 17909,
        "ko": 0
    },
    "maxResponseTime": {
        "total": 17909,
        "ok": 17909,
        "ko": 0
    },
    "meanResponseTime": {
        "total": 17909,
        "ok": 17909,
        "ko": 0
    },
    "standardDeviation": {
        "total": 0,
        "ok": 0,
        "ko": 0
    },
    "percentiles1": {
        "total": 17909,
        "ok": 17909,
        "ko": 0
    },
    "percentiles2": {
        "total": 17909,
        "ok": 17909,
        "ko": 0
    },
    "percentiles3": {
        "total": 17909,
        "ok": 17909,
        "ko": 0
    },
    "percentiles4": {
        "total": 17909,
        "ok": 17909,
        "ko": 0
    },
    "group1": {
    "name": "t < 800 ms",
    "htmlName": "t < 800 ms",
    "count": 0,
    "percentage": 0
},
    "group2": {
    "name": "800 ms <= t < 1200 ms",
    "htmlName": "t >= 800 ms <br> t < 1200 ms",
    "count": 0,
    "percentage": 0
},
    "group3": {
    "name": "t >= 1200 ms",
    "htmlName": "t >= 1200 ms",
    "count": 1,
    "percentage": 100
},
    "group4": {
    "name": "failed",
    "htmlName": "failed",
    "count": 0,
    "percentage": 0
},
    "meanNumberOfRequestsPerSecond": {
        "total": 0.007575757575757576,
        "ok": 0.007575757575757576,
        "ko": 0
    }
}
    }
}

     },"group_xui-prl-033-app-808b6": {
          "type": "GROUP",
"name": "XUI_PRL_033_ApplicationDetails",
"path": "XUI_PRL_033_ApplicationDetails",
"pathFormatted": "group_xui-prl-033-app-808b6",
"stats": {
    "name": "XUI_PRL_033_ApplicationDetails",
    "numberOfRequests": {
        "total": 1,
        "ok": 1,
        "ko": 0
    },
    "minResponseTime": {
        "total": 4806,
        "ok": 4806,
        "ko": 0
    },
    "maxResponseTime": {
        "total": 4806,
        "ok": 4806,
        "ko": 0
    },
    "meanResponseTime": {
        "total": 4806,
        "ok": 4806,
        "ko": 0
    },
    "standardDeviation": {
        "total": 0,
        "ok": 0,
        "ko": 0
    },
    "percentiles1": {
        "total": 4806,
        "ok": 4806,
        "ko": 0
    },
    "percentiles2": {
        "total": 4806,
        "ok": 4806,
        "ko": 0
    },
    "percentiles3": {
        "total": 4806,
        "ok": 4806,
        "ko": 0
    },
    "percentiles4": {
        "total": 4806,
        "ok": 4806,
        "ko": 0
    },
    "group1": {
    "name": "t < 800 ms",
    "htmlName": "t < 800 ms",
    "count": 0,
    "percentage": 0
},
    "group2": {
    "name": "800 ms <= t < 1200 ms",
    "htmlName": "t >= 800 ms <br> t < 1200 ms",
    "count": 0,
    "percentage": 0
},
    "group3": {
    "name": "t >= 1200 ms",
    "htmlName": "t >= 1200 ms",
    "count": 1,
    "percentage": 100
},
    "group4": {
    "name": "failed",
    "htmlName": "failed",
    "count": 0,
    "percentage": 0
},
    "meanNumberOfRequestsPerSecond": {
        "total": 0.007575757575757576,
        "ok": 0.007575757575757576,
        "ko": 0
    }
},
"contents": {
"req_xui-prl-033-005-797ba": {
        "type": "REQUEST",
        "name": "XUI_PRL_033_005_ApplicationDetails",
"path": "XUI_PRL_033_ApplicationDetails / XUI_PRL_033_005_ApplicationDetails",
"pathFormatted": "req_xui-prl-033-app-a89b9",
"stats": {
    "name": "XUI_PRL_033_005_ApplicationDetails",
    "numberOfRequests": {
        "total": 1,
        "ok": 1,
        "ko": 0
    },
    "minResponseTime": {
        "total": 4806,
        "ok": 4806,
        "ko": 0
    },
    "maxResponseTime": {
        "total": 4806,
        "ok": 4806,
        "ko": 0
    },
    "meanResponseTime": {
        "total": 4806,
        "ok": 4806,
        "ko": 0
    },
    "standardDeviation": {
        "total": 0,
        "ok": 0,
        "ko": 0
    },
    "percentiles1": {
        "total": 4806,
        "ok": 4806,
        "ko": 0
    },
    "percentiles2": {
        "total": 4806,
        "ok": 4806,
        "ko": 0
    },
    "percentiles3": {
        "total": 4806,
        "ok": 4806,
        "ko": 0
    },
    "percentiles4": {
        "total": 4806,
        "ok": 4806,
        "ko": 0
    },
    "group1": {
    "name": "t < 800 ms",
    "htmlName": "t < 800 ms",
    "count": 0,
    "percentage": 0
},
    "group2": {
    "name": "800 ms <= t < 1200 ms",
    "htmlName": "t >= 800 ms <br> t < 1200 ms",
    "count": 0,
    "percentage": 0
},
    "group3": {
    "name": "t >= 1200 ms",
    "htmlName": "t >= 1200 ms",
    "count": 1,
    "percentage": 100
},
    "group4": {
    "name": "failed",
    "htmlName": "failed",
    "count": 0,
    "percentage": 0
},
    "meanNumberOfRequestsPerSecond": {
        "total": 0.007575757575757576,
        "ok": 0.007575757575757576,
        "ko": 0
    }
}
    }
}

     },"group_xui-prl-034-ent-70610": {
          "type": "GROUP",
"name": "XUI_PRL_034_EnterApplicationDetails",
"path": "XUI_PRL_034_EnterApplicationDetails",
"pathFormatted": "group_xui-prl-034-ent-70610",
"stats": {
    "name": "XUI_PRL_034_EnterApplicationDetails",
    "numberOfRequests": {
        "total": 1,
        "ok": 1,
        "ko": 0
    },
    "minResponseTime": {
        "total": 1305,
        "ok": 1305,
        "ko": 0
    },
    "maxResponseTime": {
        "total": 1305,
        "ok": 1305,
        "ko": 0
    },
    "meanResponseTime": {
        "total": 1305,
        "ok": 1305,
        "ko": 0
    },
    "standardDeviation": {
        "total": 0,
        "ok": 0,
        "ko": 0
    },
    "percentiles1": {
        "total": 1305,
        "ok": 1305,
        "ko": 0
    },
    "percentiles2": {
        "total": 1305,
        "ok": 1305,
        "ko": 0
    },
    "percentiles3": {
        "total": 1305,
        "ok": 1305,
        "ko": 0
    },
    "percentiles4": {
        "total": 1305,
        "ok": 1305,
        "ko": 0
    },
    "group1": {
    "name": "t < 800 ms",
    "htmlName": "t < 800 ms",
    "count": 0,
    "percentage": 0
},
    "group2": {
    "name": "800 ms <= t < 1200 ms",
    "htmlName": "t >= 800 ms <br> t < 1200 ms",
    "count": 0,
    "percentage": 0
},
    "group3": {
    "name": "t >= 1200 ms",
    "htmlName": "t >= 1200 ms",
    "count": 1,
    "percentage": 100
},
    "group4": {
    "name": "failed",
    "htmlName": "failed",
    "count": 0,
    "percentage": 0
},
    "meanNumberOfRequestsPerSecond": {
        "total": 0.007575757575757576,
        "ok": 0.007575757575757576,
        "ko": 0
    }
},
"contents": {
"req_xui-prl-034-005-94e64": {
        "type": "REQUEST",
        "name": "XUI_PRL_034_005_EnterApplicationDetails",
"path": "XUI_PRL_034_EnterApplicationDetails / XUI_PRL_034_005_EnterApplicationDetails",
"pathFormatted": "req_xui-prl-034-ent-c27a6",
"stats": {
    "name": "XUI_PRL_034_005_EnterApplicationDetails",
    "numberOfRequests": {
        "total": 1,
        "ok": 1,
        "ko": 0
    },
    "minResponseTime": {
        "total": 1305,
        "ok": 1305,
        "ko": 0
    },
    "maxResponseTime": {
        "total": 1305,
        "ok": 1305,
        "ko": 0
    },
    "meanResponseTime": {
        "total": 1305,
        "ok": 1305,
        "ko": 0
    },
    "standardDeviation": {
        "total": 0,
        "ok": 0,
        "ko": 0
    },
    "percentiles1": {
        "total": 1305,
        "ok": 1305,
        "ko": 0
    },
    "percentiles2": {
        "total": 1305,
        "ok": 1305,
        "ko": 0
    },
    "percentiles3": {
        "total": 1305,
        "ok": 1305,
        "ko": 0
    },
    "percentiles4": {
        "total": 1305,
        "ok": 1305,
        "ko": 0
    },
    "group1": {
    "name": "t < 800 ms",
    "htmlName": "t < 800 ms",
    "count": 0,
    "percentage": 0
},
    "group2": {
    "name": "800 ms <= t < 1200 ms",
    "htmlName": "t >= 800 ms <br> t < 1200 ms",
    "count": 0,
    "percentage": 0
},
    "group3": {
    "name": "t >= 1200 ms",
    "htmlName": "t >= 1200 ms",
    "count": 1,
    "percentage": 100
},
    "group4": {
    "name": "failed",
    "htmlName": "failed",
    "count": 0,
    "percentage": 0
},
    "meanNumberOfRequestsPerSecond": {
        "total": 0.007575757575757576,
        "ok": 0.007575757575757576,
        "ko": 0
    }
}
    }
}

     },"group_xui-prl-035-sub-bc5b4": {
          "type": "GROUP",
"name": "XUI_PRL_035_SubmitApplicationDetails",
"path": "XUI_PRL_035_SubmitApplicationDetails",
"pathFormatted": "group_xui-prl-035-sub-bc5b4",
"stats": {
    "name": "XUI_PRL_035_SubmitApplicationDetails",
    "numberOfRequests": {
        "total": 1,
        "ok": 1,
        "ko": 0
    },
    "minResponseTime": {
        "total": 11924,
        "ok": 11924,
        "ko": 0
    },
    "maxResponseTime": {
        "total": 11924,
        "ok": 11924,
        "ko": 0
    },
    "meanResponseTime": {
        "total": 11924,
        "ok": 11924,
        "ko": 0
    },
    "standardDeviation": {
        "total": 0,
        "ok": 0,
        "ko": 0
    },
    "percentiles1": {
        "total": 11924,
        "ok": 11924,
        "ko": 0
    },
    "percentiles2": {
        "total": 11924,
        "ok": 11924,
        "ko": 0
    },
    "percentiles3": {
        "total": 11924,
        "ok": 11924,
        "ko": 0
    },
    "percentiles4": {
        "total": 11924,
        "ok": 11924,
        "ko": 0
    },
    "group1": {
    "name": "t < 800 ms",
    "htmlName": "t < 800 ms",
    "count": 0,
    "percentage": 0
},
    "group2": {
    "name": "800 ms <= t < 1200 ms",
    "htmlName": "t >= 800 ms <br> t < 1200 ms",
    "count": 0,
    "percentage": 0
},
    "group3": {
    "name": "t >= 1200 ms",
    "htmlName": "t >= 1200 ms",
    "count": 1,
    "percentage": 100
},
    "group4": {
    "name": "failed",
    "htmlName": "failed",
    "count": 0,
    "percentage": 0
},
    "meanNumberOfRequestsPerSecond": {
        "total": 0.007575757575757576,
        "ok": 0.007575757575757576,
        "ko": 0
    }
},
"contents": {
"req_xui-prl-035-005-ee61f": {
        "type": "REQUEST",
        "name": "XUI_PRL_035_005_SubmitApplicationDetails",
"path": "XUI_PRL_035_SubmitApplicationDetails / XUI_PRL_035_005_SubmitApplicationDetails",
"pathFormatted": "req_xui-prl-035-sub-99fff",
"stats": {
    "name": "XUI_PRL_035_005_SubmitApplicationDetails",
    "numberOfRequests": {
        "total": 1,
        "ok": 1,
        "ko": 0
    },
    "minResponseTime": {
        "total": 11924,
        "ok": 11924,
        "ko": 0
    },
    "maxResponseTime": {
        "total": 11924,
        "ok": 11924,
        "ko": 0
    },
    "meanResponseTime": {
        "total": 11924,
        "ok": 11924,
        "ko": 0
    },
    "standardDeviation": {
        "total": 0,
        "ok": 0,
        "ko": 0
    },
    "percentiles1": {
        "total": 11924,
        "ok": 11924,
        "ko": 0
    },
    "percentiles2": {
        "total": 11924,
        "ok": 11924,
        "ko": 0
    },
    "percentiles3": {
        "total": 11924,
        "ok": 11924,
        "ko": 0
    },
    "percentiles4": {
        "total": 11924,
        "ok": 11924,
        "ko": 0
    },
    "group1": {
    "name": "t < 800 ms",
    "htmlName": "t < 800 ms",
    "count": 0,
    "percentage": 0
},
    "group2": {
    "name": "800 ms <= t < 1200 ms",
    "htmlName": "t >= 800 ms <br> t < 1200 ms",
    "count": 0,
    "percentage": 0
},
    "group3": {
    "name": "t >= 1200 ms",
    "htmlName": "t >= 1200 ms",
    "count": 1,
    "percentage": 100
},
    "group4": {
    "name": "failed",
    "htmlName": "failed",
    "count": 0,
    "percentage": 0
},
    "meanNumberOfRequestsPerSecond": {
        "total": 0.007575757575757576,
        "ok": 0.007575757575757576,
        "ko": 0
    }
}
    }
}

     },"group_xui-prl-036-sub-032e4": {
          "type": "GROUP",
"name": "XUI_PRL_036_SubmitAndPay",
"path": "XUI_PRL_036_SubmitAndPay",
"pathFormatted": "group_xui-prl-036-sub-032e4",
"stats": {
    "name": "XUI_PRL_036_SubmitAndPay",
    "numberOfRequests": {
        "total": 1,
        "ok": 1,
        "ko": 0
    },
    "minResponseTime": {
        "total": 9913,
        "ok": 9913,
        "ko": 0
    },
    "maxResponseTime": {
        "total": 9913,
        "ok": 9913,
        "ko": 0
    },
    "meanResponseTime": {
        "total": 9913,
        "ok": 9913,
        "ko": 0
    },
    "standardDeviation": {
        "total": 0,
        "ok": 0,
        "ko": 0
    },
    "percentiles1": {
        "total": 9913,
        "ok": 9913,
        "ko": 0
    },
    "percentiles2": {
        "total": 9913,
        "ok": 9913,
        "ko": 0
    },
    "percentiles3": {
        "total": 9913,
        "ok": 9913,
        "ko": 0
    },
    "percentiles4": {
        "total": 9913,
        "ok": 9913,
        "ko": 0
    },
    "group1": {
    "name": "t < 800 ms",
    "htmlName": "t < 800 ms",
    "count": 0,
    "percentage": 0
},
    "group2": {
    "name": "800 ms <= t < 1200 ms",
    "htmlName": "t >= 800 ms <br> t < 1200 ms",
    "count": 0,
    "percentage": 0
},
    "group3": {
    "name": "t >= 1200 ms",
    "htmlName": "t >= 1200 ms",
    "count": 1,
    "percentage": 100
},
    "group4": {
    "name": "failed",
    "htmlName": "failed",
    "count": 0,
    "percentage": 0
},
    "meanNumberOfRequestsPerSecond": {
        "total": 0.007575757575757576,
        "ok": 0.007575757575757576,
        "ko": 0
    }
},
"contents": {
"req_xui-prl-036-005-0001d": {
        "type": "REQUEST",
        "name": "XUI_PRL_036_005_SubmitAndPay",
"path": "XUI_PRL_036_SubmitAndPay / XUI_PRL_036_005_SubmitAndPay",
"pathFormatted": "req_xui-prl-036-sub-8299f",
"stats": {
    "name": "XUI_PRL_036_005_SubmitAndPay",
    "numberOfRequests": {
        "total": 1,
        "ok": 1,
        "ko": 0
    },
    "minResponseTime": {
        "total": 9913,
        "ok": 9913,
        "ko": 0
    },
    "maxResponseTime": {
        "total": 9913,
        "ok": 9913,
        "ko": 0
    },
    "meanResponseTime": {
        "total": 9913,
        "ok": 9913,
        "ko": 0
    },
    "standardDeviation": {
        "total": 0,
        "ok": 0,
        "ko": 0
    },
    "percentiles1": {
        "total": 9913,
        "ok": 9913,
        "ko": 0
    },
    "percentiles2": {
        "total": 9913,
        "ok": 9913,
        "ko": 0
    },
    "percentiles3": {
        "total": 9913,
        "ok": 9913,
        "ko": 0
    },
    "percentiles4": {
        "total": 9913,
        "ok": 9913,
        "ko": 0
    },
    "group1": {
    "name": "t < 800 ms",
    "htmlName": "t < 800 ms",
    "count": 0,
    "percentage": 0
},
    "group2": {
    "name": "800 ms <= t < 1200 ms",
    "htmlName": "t >= 800 ms <br> t < 1200 ms",
    "count": 0,
    "percentage": 0
},
    "group3": {
    "name": "t >= 1200 ms",
    "htmlName": "t >= 1200 ms",
    "count": 1,
    "percentage": 100
},
    "group4": {
    "name": "failed",
    "htmlName": "failed",
    "count": 0,
    "percentage": 0
},
    "meanNumberOfRequestsPerSecond": {
        "total": 0.007575757575757576,
        "ok": 0.007575757575757576,
        "ko": 0
    }
}
    }
}

     },"group_xui-prl-037-con-14f78": {
          "type": "GROUP",
"name": "XUI_PRL_037_ConfidentialityStatement",
"path": "XUI_PRL_037_ConfidentialityStatement",
"pathFormatted": "group_xui-prl-037-con-14f78",
"stats": {
    "name": "XUI_PRL_037_ConfidentialityStatement",
    "numberOfRequests": {
        "total": 1,
        "ok": 1,
        "ko": 0
    },
    "minResponseTime": {
        "total": 2329,
        "ok": 2329,
        "ko": 0
    },
    "maxResponseTime": {
        "total": 2329,
        "ok": 2329,
        "ko": 0
    },
    "meanResponseTime": {
        "total": 2329,
        "ok": 2329,
        "ko": 0
    },
    "standardDeviation": {
        "total": 0,
        "ok": 0,
        "ko": 0
    },
    "percentiles1": {
        "total": 2329,
        "ok": 2329,
        "ko": 0
    },
    "percentiles2": {
        "total": 2329,
        "ok": 2329,
        "ko": 0
    },
    "percentiles3": {
        "total": 2329,
        "ok": 2329,
        "ko": 0
    },
    "percentiles4": {
        "total": 2329,
        "ok": 2329,
        "ko": 0
    },
    "group1": {
    "name": "t < 800 ms",
    "htmlName": "t < 800 ms",
    "count": 0,
    "percentage": 0
},
    "group2": {
    "name": "800 ms <= t < 1200 ms",
    "htmlName": "t >= 800 ms <br> t < 1200 ms",
    "count": 0,
    "percentage": 0
},
    "group3": {
    "name": "t >= 1200 ms",
    "htmlName": "t >= 1200 ms",
    "count": 1,
    "percentage": 100
},
    "group4": {
    "name": "failed",
    "htmlName": "failed",
    "count": 0,
    "percentage": 0
},
    "meanNumberOfRequestsPerSecond": {
        "total": 0.007575757575757576,
        "ok": 0.007575757575757576,
        "ko": 0
    }
},
"contents": {
"req_xui-prl-037-005-8420c": {
        "type": "REQUEST",
        "name": "XUI_PRL_037_005_ConfidentialityStatement",
"path": "XUI_PRL_037_ConfidentialityStatement / XUI_PRL_037_005_ConfidentialityStatement",
"pathFormatted": "req_xui-prl-037-con-c966b",
"stats": {
    "name": "XUI_PRL_037_005_ConfidentialityStatement",
    "numberOfRequests": {
        "total": 1,
        "ok": 1,
        "ko": 0
    },
    "minResponseTime": {
        "total": 2329,
        "ok": 2329,
        "ko": 0
    },
    "maxResponseTime": {
        "total": 2329,
        "ok": 2329,
        "ko": 0
    },
    "meanResponseTime": {
        "total": 2329,
        "ok": 2329,
        "ko": 0
    },
    "standardDeviation": {
        "total": 0,
        "ok": 0,
        "ko": 0
    },
    "percentiles1": {
        "total": 2329,
        "ok": 2329,
        "ko": 0
    },
    "percentiles2": {
        "total": 2329,
        "ok": 2329,
        "ko": 0
    },
    "percentiles3": {
        "total": 2329,
        "ok": 2329,
        "ko": 0
    },
    "percentiles4": {
        "total": 2329,
        "ok": 2329,
        "ko": 0
    },
    "group1": {
    "name": "t < 800 ms",
    "htmlName": "t < 800 ms",
    "count": 0,
    "percentage": 0
},
    "group2": {
    "name": "800 ms <= t < 1200 ms",
    "htmlName": "t >= 800 ms <br> t < 1200 ms",
    "count": 0,
    "percentage": 0
},
    "group3": {
    "name": "t >= 1200 ms",
    "htmlName": "t >= 1200 ms",
    "count": 1,
    "percentage": 100
},
    "group4": {
    "name": "failed",
    "htmlName": "failed",
    "count": 0,
    "percentage": 0
},
    "meanNumberOfRequestsPerSecond": {
        "total": 0.007575757575757576,
        "ok": 0.007575757575757576,
        "ko": 0
    }
}
    }
}

     },"group_xui-prl-038-dec-c3d69": {
          "type": "GROUP",
"name": "XUI_PRL_038_Declaration",
"path": "XUI_PRL_038_Declaration",
"pathFormatted": "group_xui-prl-038-dec-c3d69",
"stats": {
    "name": "XUI_PRL_038_Declaration",
    "numberOfRequests": {
        "total": 1,
        "ok": 1,
        "ko": 0
    },
    "minResponseTime": {
        "total": 853,
        "ok": 853,
        "ko": 0
    },
    "maxResponseTime": {
        "total": 853,
        "ok": 853,
        "ko": 0
    },
    "meanResponseTime": {
        "total": 853,
        "ok": 853,
        "ko": 0
    },
    "standardDeviation": {
        "total": 0,
        "ok": 0,
        "ko": 0
    },
    "percentiles1": {
        "total": 853,
        "ok": 853,
        "ko": 0
    },
    "percentiles2": {
        "total": 853,
        "ok": 853,
        "ko": 0
    },
    "percentiles3": {
        "total": 853,
        "ok": 853,
        "ko": 0
    },
    "percentiles4": {
        "total": 853,
        "ok": 853,
        "ko": 0
    },
    "group1": {
    "name": "t < 800 ms",
    "htmlName": "t < 800 ms",
    "count": 0,
    "percentage": 0
},
    "group2": {
    "name": "800 ms <= t < 1200 ms",
    "htmlName": "t >= 800 ms <br> t < 1200 ms",
    "count": 1,
    "percentage": 100
},
    "group3": {
    "name": "t >= 1200 ms",
    "htmlName": "t >= 1200 ms",
    "count": 0,
    "percentage": 0
},
    "group4": {
    "name": "failed",
    "htmlName": "failed",
    "count": 0,
    "percentage": 0
},
    "meanNumberOfRequestsPerSecond": {
        "total": 0.007575757575757576,
        "ok": 0.007575757575757576,
        "ko": 0
    }
},
"contents": {
"req_xui-prl-038-005-924fe": {
        "type": "REQUEST",
        "name": "XUI_PRL_038_005_Declaration",
"path": "XUI_PRL_038_Declaration / XUI_PRL_038_005_Declaration",
"pathFormatted": "req_xui-prl-038-dec-e86ba",
"stats": {
    "name": "XUI_PRL_038_005_Declaration",
    "numberOfRequests": {
        "total": 1,
        "ok": 1,
        "ko": 0
    },
    "minResponseTime": {
        "total": 853,
        "ok": 853,
        "ko": 0
    },
    "maxResponseTime": {
        "total": 853,
        "ok": 853,
        "ko": 0
    },
    "meanResponseTime": {
        "total": 853,
        "ok": 853,
        "ko": 0
    },
    "standardDeviation": {
        "total": 0,
        "ok": 0,
        "ko": 0
    },
    "percentiles1": {
        "total": 853,
        "ok": 853,
        "ko": 0
    },
    "percentiles2": {
        "total": 853,
        "ok": 853,
        "ko": 0
    },
    "percentiles3": {
        "total": 853,
        "ok": 853,
        "ko": 0
    },
    "percentiles4": {
        "total": 853,
        "ok": 853,
        "ko": 0
    },
    "group1": {
    "name": "t < 800 ms",
    "htmlName": "t < 800 ms",
    "count": 0,
    "percentage": 0
},
    "group2": {
    "name": "800 ms <= t < 1200 ms",
    "htmlName": "t >= 800 ms <br> t < 1200 ms",
    "count": 1,
    "percentage": 100
},
    "group3": {
    "name": "t >= 1200 ms",
    "htmlName": "t >= 1200 ms",
    "count": 0,
    "percentage": 0
},
    "group4": {
    "name": "failed",
    "htmlName": "failed",
    "count": 0,
    "percentage": 0
},
    "meanNumberOfRequestsPerSecond": {
        "total": 0.007575757575757576,
        "ok": 0.007575757575757576,
        "ko": 0
    }
}
    }
}

     },"group_xui-prl-039-con-bc73f": {
          "type": "GROUP",
"name": "XUI_PRL_039_Continue",
"path": "XUI_PRL_039_Continue",
"pathFormatted": "group_xui-prl-039-con-bc73f",
"stats": {
    "name": "XUI_PRL_039_Continue",
    "numberOfRequests": {
        "total": 1,
        "ok": 1,
        "ko": 0
    },
    "minResponseTime": {
        "total": 1316,
        "ok": 1316,
        "ko": 0
    },
    "maxResponseTime": {
        "total": 1316,
        "ok": 1316,
        "ko": 0
    },
    "meanResponseTime": {
        "total": 1316,
        "ok": 1316,
        "ko": 0
    },
    "standardDeviation": {
        "total": 0,
        "ok": 0,
        "ko": 0
    },
    "percentiles1": {
        "total": 1316,
        "ok": 1316,
        "ko": 0
    },
    "percentiles2": {
        "total": 1316,
        "ok": 1316,
        "ko": 0
    },
    "percentiles3": {
        "total": 1316,
        "ok": 1316,
        "ko": 0
    },
    "percentiles4": {
        "total": 1316,
        "ok": 1316,
        "ko": 0
    },
    "group1": {
    "name": "t < 800 ms",
    "htmlName": "t < 800 ms",
    "count": 0,
    "percentage": 0
},
    "group2": {
    "name": "800 ms <= t < 1200 ms",
    "htmlName": "t >= 800 ms <br> t < 1200 ms",
    "count": 0,
    "percentage": 0
},
    "group3": {
    "name": "t >= 1200 ms",
    "htmlName": "t >= 1200 ms",
    "count": 1,
    "percentage": 100
},
    "group4": {
    "name": "failed",
    "htmlName": "failed",
    "count": 0,
    "percentage": 0
},
    "meanNumberOfRequestsPerSecond": {
        "total": 0.007575757575757576,
        "ok": 0.007575757575757576,
        "ko": 0
    }
},
"contents": {
"req_xui-prl-039-005-ece55": {
        "type": "REQUEST",
        "name": "XUI_PRL_039_005_Continue",
"path": "XUI_PRL_039_Continue / XUI_PRL_039_005_Continue",
"pathFormatted": "req_xui-prl-039-con-eb4b0",
"stats": {
    "name": "XUI_PRL_039_005_Continue",
    "numberOfRequests": {
        "total": 1,
        "ok": 1,
        "ko": 0
    },
    "minResponseTime": {
        "total": 1316,
        "ok": 1316,
        "ko": 0
    },
    "maxResponseTime": {
        "total": 1316,
        "ok": 1316,
        "ko": 0
    },
    "meanResponseTime": {
        "total": 1316,
        "ok": 1316,
        "ko": 0
    },
    "standardDeviation": {
        "total": 0,
        "ok": 0,
        "ko": 0
    },
    "percentiles1": {
        "total": 1316,
        "ok": 1316,
        "ko": 0
    },
    "percentiles2": {
        "total": 1316,
        "ok": 1316,
        "ko": 0
    },
    "percentiles3": {
        "total": 1316,
        "ok": 1316,
        "ko": 0
    },
    "percentiles4": {
        "total": 1316,
        "ok": 1316,
        "ko": 0
    },
    "group1": {
    "name": "t < 800 ms",
    "htmlName": "t < 800 ms",
    "count": 0,
    "percentage": 0
},
    "group2": {
    "name": "800 ms <= t < 1200 ms",
    "htmlName": "t >= 800 ms <br> t < 1200 ms",
    "count": 0,
    "percentage": 0
},
    "group3": {
    "name": "t >= 1200 ms",
    "htmlName": "t >= 1200 ms",
    "count": 1,
    "percentage": 100
},
    "group4": {
    "name": "failed",
    "htmlName": "failed",
    "count": 0,
    "percentage": 0
},
    "meanNumberOfRequestsPerSecond": {
        "total": 0.007575757575757576,
        "ok": 0.007575757575757576,
        "ko": 0
    }
}
    }
}

     },"group_xui-prl-040-con-f1ffa": {
          "type": "GROUP",
"name": "XUI_PRL_040_Continue",
"path": "XUI_PRL_040_Continue",
"pathFormatted": "group_xui-prl-040-con-f1ffa",
"stats": {
    "name": "XUI_PRL_040_Continue",
    "numberOfRequests": {
        "total": 1,
        "ok": 1,
        "ko": 0
    },
    "minResponseTime": {
        "total": 14705,
        "ok": 14705,
        "ko": 0
    },
    "maxResponseTime": {
        "total": 14705,
        "ok": 14705,
        "ko": 0
    },
    "meanResponseTime": {
        "total": 14705,
        "ok": 14705,
        "ko": 0
    },
    "standardDeviation": {
        "total": 0,
        "ok": 0,
        "ko": 0
    },
    "percentiles1": {
        "total": 14705,
        "ok": 14705,
        "ko": 0
    },
    "percentiles2": {
        "total": 14705,
        "ok": 14705,
        "ko": 0
    },
    "percentiles3": {
        "total": 14705,
        "ok": 14705,
        "ko": 0
    },
    "percentiles4": {
        "total": 14705,
        "ok": 14705,
        "ko": 0
    },
    "group1": {
    "name": "t < 800 ms",
    "htmlName": "t < 800 ms",
    "count": 0,
    "percentage": 0
},
    "group2": {
    "name": "800 ms <= t < 1200 ms",
    "htmlName": "t >= 800 ms <br> t < 1200 ms",
    "count": 0,
    "percentage": 0
},
    "group3": {
    "name": "t >= 1200 ms",
    "htmlName": "t >= 1200 ms",
    "count": 1,
    "percentage": 100
},
    "group4": {
    "name": "failed",
    "htmlName": "failed",
    "count": 0,
    "percentage": 0
},
    "meanNumberOfRequestsPerSecond": {
        "total": 0.007575757575757576,
        "ok": 0.007575757575757576,
        "ko": 0
    }
},
"contents": {
"req_xui-prl-039-005-ece55": {
        "type": "REQUEST",
        "name": "XUI_PRL_039_005_Continue",
"path": "XUI_PRL_040_Continue / XUI_PRL_039_005_Continue",
"pathFormatted": "req_xui-prl-040-con-0da90",
"stats": {
    "name": "XUI_PRL_039_005_Continue",
    "numberOfRequests": {
        "total": 1,
        "ok": 1,
        "ko": 0
    },
    "minResponseTime": {
        "total": 14705,
        "ok": 14705,
        "ko": 0
    },
    "maxResponseTime": {
        "total": 14705,
        "ok": 14705,
        "ko": 0
    },
    "meanResponseTime": {
        "total": 14705,
        "ok": 14705,
        "ko": 0
    },
    "standardDeviation": {
        "total": 0,
        "ok": 0,
        "ko": 0
    },
    "percentiles1": {
        "total": 14705,
        "ok": 14705,
        "ko": 0
    },
    "percentiles2": {
        "total": 14705,
        "ok": 14705,
        "ko": 0
    },
    "percentiles3": {
        "total": 14705,
        "ok": 14705,
        "ko": 0
    },
    "percentiles4": {
        "total": 14705,
        "ok": 14705,
        "ko": 0
    },
    "group1": {
    "name": "t < 800 ms",
    "htmlName": "t < 800 ms",
    "count": 0,
    "percentage": 0
},
    "group2": {
    "name": "800 ms <= t < 1200 ms",
    "htmlName": "t >= 800 ms <br> t < 1200 ms",
    "count": 0,
    "percentage": 0
},
    "group3": {
    "name": "t >= 1200 ms",
    "htmlName": "t >= 1200 ms",
    "count": 1,
    "percentage": 100
},
    "group4": {
    "name": "failed",
    "htmlName": "failed",
    "count": 0,
    "percentage": 0
},
    "meanNumberOfRequestsPerSecond": {
        "total": 0.007575757575757576,
        "ok": 0.007575757575757576,
        "ko": 0
    }
}
    }
}

     },"group_xui-prl-042-dum-09924": {
          "type": "GROUP",
"name": "XUI_PRL_042_DummyPaymentConfirmation ",
"path": "XUI_PRL_042_DummyPaymentConfirmation ",
"pathFormatted": "group_xui-prl-042-dum-09924",
"stats": {
    "name": "XUI_PRL_042_DummyPaymentConfirmation ",
    "numberOfRequests": {
        "total": 1,
        "ok": 1,
        "ko": 0
    },
    "minResponseTime": {
        "total": 2086,
        "ok": 2086,
        "ko": 0
    },
    "maxResponseTime": {
        "total": 2086,
        "ok": 2086,
        "ko": 0
    },
    "meanResponseTime": {
        "total": 2086,
        "ok": 2086,
        "ko": 0
    },
    "standardDeviation": {
        "total": 0,
        "ok": 0,
        "ko": 0
    },
    "percentiles1": {
        "total": 2086,
        "ok": 2086,
        "ko": 0
    },
    "percentiles2": {
        "total": 2086,
        "ok": 2086,
        "ko": 0
    },
    "percentiles3": {
        "total": 2086,
        "ok": 2086,
        "ko": 0
    },
    "percentiles4": {
        "total": 2086,
        "ok": 2086,
        "ko": 0
    },
    "group1": {
    "name": "t < 800 ms",
    "htmlName": "t < 800 ms",
    "count": 0,
    "percentage": 0
},
    "group2": {
    "name": "800 ms <= t < 1200 ms",
    "htmlName": "t >= 800 ms <br> t < 1200 ms",
    "count": 0,
    "percentage": 0
},
    "group3": {
    "name": "t >= 1200 ms",
    "htmlName": "t >= 1200 ms",
    "count": 1,
    "percentage": 100
},
    "group4": {
    "name": "failed",
    "htmlName": "failed",
    "count": 0,
    "percentage": 0
},
    "meanNumberOfRequestsPerSecond": {
        "total": 0.007575757575757576,
        "ok": 0.007575757575757576,
        "ko": 0
    }
},
"contents": {
"req_xui-prl-040-005-4d7d3": {
        "type": "REQUEST",
        "name": "XUI_PRL_040_005_DummyPaymentConfirmation ",
"path": "XUI_PRL_042_DummyPaymentConfirmation  / XUI_PRL_040_005_DummyPaymentConfirmation ",
"pathFormatted": "req_xui-prl-042-dum-4e35b",
"stats": {
    "name": "XUI_PRL_040_005_DummyPaymentConfirmation ",
    "numberOfRequests": {
        "total": 1,
        "ok": 1,
        "ko": 0
    },
    "minResponseTime": {
        "total": 2086,
        "ok": 2086,
        "ko": 0
    },
    "maxResponseTime": {
        "total": 2086,
        "ok": 2086,
        "ko": 0
    },
    "meanResponseTime": {
        "total": 2086,
        "ok": 2086,
        "ko": 0
    },
    "standardDeviation": {
        "total": 0,
        "ok": 0,
        "ko": 0
    },
    "percentiles1": {
        "total": 2086,
        "ok": 2086,
        "ko": 0
    },
    "percentiles2": {
        "total": 2086,
        "ok": 2086,
        "ko": 0
    },
    "percentiles3": {
        "total": 2086,
        "ok": 2086,
        "ko": 0
    },
    "percentiles4": {
        "total": 2086,
        "ok": 2086,
        "ko": 0
    },
    "group1": {
    "name": "t < 800 ms",
    "htmlName": "t < 800 ms",
    "count": 0,
    "percentage": 0
},
    "group2": {
    "name": "800 ms <= t < 1200 ms",
    "htmlName": "t >= 800 ms <br> t < 1200 ms",
    "count": 0,
    "percentage": 0
},
    "group3": {
    "name": "t >= 1200 ms",
    "htmlName": "t >= 1200 ms",
    "count": 1,
    "percentage": 100
},
    "group4": {
    "name": "failed",
    "htmlName": "failed",
    "count": 0,
    "percentage": 0
},
    "meanNumberOfRequestsPerSecond": {
        "total": 0.007575757575757576,
        "ok": 0.007575757575757576,
        "ko": 0
    }
}
    }
}

     },"group_xui-prl-041-pay-44f70": {
          "type": "GROUP",
"name": "XUI_PRL_041_PaymentOption",
"path": "XUI_PRL_041_PaymentOption",
"pathFormatted": "group_xui-prl-041-pay-44f70",
"stats": {
    "name": "XUI_PRL_041_PaymentOption",
    "numberOfRequests": {
        "total": 1,
        "ok": 0,
        "ko": 1
    },
    "minResponseTime": {
        "total": 5083,
        "ok": 0,
        "ko": 5083
    },
    "maxResponseTime": {
        "total": 5083,
        "ok": 0,
        "ko": 5083
    },
    "meanResponseTime": {
        "total": 5083,
        "ok": 0,
        "ko": 5083
    },
    "standardDeviation": {
        "total": 0,
        "ok": 0,
        "ko": 0
    },
    "percentiles1": {
        "total": 5083,
        "ok": 0,
        "ko": 5083
    },
    "percentiles2": {
        "total": 5083,
        "ok": 0,
        "ko": 5083
    },
    "percentiles3": {
        "total": 5083,
        "ok": 0,
        "ko": 5083
    },
    "percentiles4": {
        "total": 5083,
        "ok": 0,
        "ko": 5083
    },
    "group1": {
    "name": "t < 800 ms",
    "htmlName": "t < 800 ms",
    "count": 0,
    "percentage": 0
},
    "group2": {
    "name": "800 ms <= t < 1200 ms",
    "htmlName": "t >= 800 ms <br> t < 1200 ms",
    "count": 0,
    "percentage": 0
},
    "group3": {
    "name": "t >= 1200 ms",
    "htmlName": "t >= 1200 ms",
    "count": 0,
    "percentage": 0
},
    "group4": {
    "name": "failed",
    "htmlName": "failed",
    "count": 1,
    "percentage": 100
},
    "meanNumberOfRequestsPerSecond": {
        "total": 0.007575757575757576,
        "ok": 0,
        "ko": 0.007575757575757576
    }
},
"contents": {
"req_xui-prl-041-005-a3fe6": {
        "type": "REQUEST",
        "name": "XUI_PRL_041_005_PaymentOption",
"path": "XUI_PRL_041_PaymentOption / XUI_PRL_041_005_PaymentOption",
"pathFormatted": "req_xui-prl-041-pay-e128b",
"stats": {
    "name": "XUI_PRL_041_005_PaymentOption",
    "numberOfRequests": {
        "total": 1,
        "ok": 0,
        "ko": 1
    },
    "minResponseTime": {
        "total": 5083,
        "ok": 0,
        "ko": 5083
    },
    "maxResponseTime": {
        "total": 5083,
        "ok": 0,
        "ko": 5083
    },
    "meanResponseTime": {
        "total": 5083,
        "ok": 0,
        "ko": 5083
    },
    "standardDeviation": {
        "total": 0,
        "ok": 0,
        "ko": 0
    },
    "percentiles1": {
        "total": 5083,
        "ok": 0,
        "ko": 5083
    },
    "percentiles2": {
        "total": 5083,
        "ok": 0,
        "ko": 5083
    },
    "percentiles3": {
        "total": 5083,
        "ok": 0,
        "ko": 5083
    },
    "percentiles4": {
        "total": 5083,
        "ok": 0,
        "ko": 5083
    },
    "group1": {
    "name": "t < 800 ms",
    "htmlName": "t < 800 ms",
    "count": 0,
    "percentage": 0
},
    "group2": {
    "name": "800 ms <= t < 1200 ms",
    "htmlName": "t >= 800 ms <br> t < 1200 ms",
    "count": 0,
    "percentage": 0
},
    "group3": {
    "name": "t >= 1200 ms",
    "htmlName": "t >= 1200 ms",
    "count": 0,
    "percentage": 0
},
    "group4": {
    "name": "failed",
    "htmlName": "failed",
    "count": 1,
    "percentage": 100
},
    "meanNumberOfRequestsPerSecond": {
        "total": 0.007575757575757576,
        "ok": 0,
        "ko": 0.007575757575757576
    }
}
    }
}

     }
}

}