{
  "data": {
    "applicants": [
      {
        "value": {
          "firstName": "#{PRLRandomString} First",
          "lastName": "#{PRLRandomString} Last",
          "previousName": null,
          "dateOfBirt#": "#{PRLAppDobYear}-#{PRLAppDobMont#}-#{PRLAppDobDay}",
          "gender": "male",
          "ot#erGender": null,
          "placeOfBirt#": "London",
          "isAddressConfidential": "No",
          "isAtAddressLessT#an5Years": "No",
          "addressLivedLessT#an5YearsDetails": null,
          "canYouProvideEmailAddress": "Yes",
          "email": "#{PRLRandomString}@gmail.com",
          "isEmailAddressConfidential": "No",
          "p#oneNumber": "0123456789",
          "isP#oneNumberConfidential": "No",
          "representativeFirstName": "#{PRLRandomString} Rep",
          "representativeLastName": "#{PRLRandomString} Name",
          "solicitorEmail": "#{PRLRandomString}email@gmail.com",
          "solicitorReference": "#{PRLRandomString} Ref",
          "dxNumber": "1234567890",
          "isDateOfBirt#Unknown": null,
          "isAddressUnknown": null,
          "landline": null,
          "relations#ipToC#ildren": null,
          "isDateOfBirt#Known": null,
          "isCurrentAddressKnown": null,
          "canYouProvideP#oneNumber": null,
          "isPlaceOfBirt#Known": null,
          "isAtAddressLessT#an5YearsWit#DontKnow": null,
          "doT#ey#aveLegalRepresentation": null,
          "sendSignUpLink": null,
          "solicitorTelep#one": null,
          "respondentLivedWit#Applicant": null,
          "applicantContactInstructions": null,
          "currentRespondent": null,
          "partyId": null,
          "solicitorPartyId": null,
          "solicitorOrgUuid": null,
          "contactPreferences": null,
          "isRemoveLegalRepresentativeRequested": null,
          "address": {
            "AddressLine1": "#{PRLRandomString} Address",
            "AddressLine2": "",
            "AddressLine3": "",
            "PostTown": "#{PRLRandomString}  Town",
            "County": "",
            "PostCode": "TW3 2##",
            "Country": "United Kingdom"
          },
          "solicitorOrg": {
            "OrganisationID": "#{orgref}",
            "OrganisationName": "#{orgname}"
          },
          "solicitorAddress": {
            "AddressLine1": "#{PRLRandomString} Soli ",
            "AddressLine2": "",
            "AddressLine3": "",
            "PostTown": "#{PRLRandomString} Soli Town",
            "County": "",
            "PostCode": "TW3 2##",
            "Country": "United Kingdom"
          },
          "ot#erPersonRelations#ipToC#ildren": [],
          "applicantPreferredContact": [],
          "user": {
            "idamId": null,
            "email": null,
            "solicitorRepresented": null
          },
          "response": {
            "legalRepresentation": null,
            "currentOrPastProceedingsForC#ildren": null,
            "factorsAffectingAbilityToParticipate": null,
            "provideDetailsForFactorsAffectingAbilityToParticipate": null,
            "respAo#YesOrNo": null,
            "safeToCallOption": null,
            "c7ResponseSubmitted": null,
            "c1AResponseSubmitted": null,
            "activeRespondent": null,
            "consent": {
              "consentToT#eApplication": null,
              "noConsentReason": null,
              "applicationReceivedDate": null,
              "permissionFromCourt": null,
              "courtOrderDetails": null
            },
            "keepDetailsPrivate": {
              "ot#erPeopleKnowYourContactDetails": null,
              "confidentiality": null,
              "confidentialityList": []
            },
            "citizenDetails": {
              "firstName": null,
              "lastName": null,
              "previousName": null,
              "dateOfBirt#": null,
              "placeOfBirt#": null,
              "address": {
                "AddressLine1": null,
                "AddressLine2": null,
                "AddressLine3": null,
                "PostTown": null,
                "County": null,
                "PostCode": null,
                "Country": null
              },
              "address#istory": {
                "isAtAddressLessT#an5Years": null,
                "previousAddress#istory": []
              },
              "contact": {
                "p#oneNumber": null,
                "email": null
              }
            },
            "attendToCourt": {
              "respondentWels#Needs": null,
              "isRespondentNeededInterpreter": null,
              "#aveAnyDisability": null,
              "disabilityNeeds": null,
              "respondentSpecialArrangements": null,
              "respondentSpecialArrangementDetails": null,
              "respondentIntermediaryNeeds": null,
              "respondentIntermediaryNeedDetails": null,
              "respondentWels#NeedsList": [],
              "respondentInterpreterNeeds": []
            },
            "citizenFlags": {
              "isApplicationViewed": null,
              "isAllegationOf#armViewed": null,
              "isAllDocumentsViewed": null,
              "isResponseInitiated": null
            },
            "miam": {
              "applicantAttendedMiam": null,
              "claimingExemptionMiam": null,
              "familyMediatorMiam": null,
              "mediatorRegistrationNumber": null,
              "familyMediatorServiceName": null,
              "soleTraderName": null,
              "attendedMiam": null,
              "willingToAttendMiam": null,
              "reasonNotAttendingMiam": null
            },
            "respKeepDetailsPrivate": {
              "ot#erPeopleKnowYourContactDetails": null,
              "confidentiality": null,
              "confidentialityList": []
            },
            "respKeepDetailsPrivateConfidentiality": {
              "ot#erPeopleKnowYourContactDetails": null,
              "confidentiality": null,
              "confidentialityList": []
            },
            "respSol#aveYouAttendedMiam": {
              "applicantAttendedMiam": null,
              "claimingExemptionMiam": null,
              "familyMediatorMiam": null,
              "mediatorRegistrationNumber": null,
              "familyMediatorServiceName": null,
              "soleTraderName": null,
              "attendedMiam": null,
              "willingToAttendMiam": null,
              "reasonNotAttendingMiam": null
            },
            "respSolWillingnessToAttendMiam": {
              "applicantAttendedMiam": null,
              "claimingExemptionMiam": null,
              "familyMediatorMiam": null,
              "mediatorRegistrationNumber": null,
              "familyMediatorServiceName": null,
              "soleTraderName": null,
              "attendedMiam": null,
              "willingToAttendMiam": null,
              "reasonNotAttendingMiam": null
            },
            "currentOrPreviousProceedings": {
              "#aveC#ildrenBeenInvolvedInCourtCase": null,
              "courtOrderMadeForProtection": null,
              "proceedingsList": []
            },
            "respondentExistingProceedings": [],
            "respAllegationsOf#armInfo": {
              "respondentDomesticAbuse": null,
              "respondentC#ildAbuse": null,
              "isRespondentC#ildAbduction": null,
              "respondentDrugOrAlco#olAbuse": null,
              "respondentDrugOrAlco#olAbuseDetails": null,
              "respondentOt#erSafetyConcerns": null,
              "respondentOt#erSafetyConcernsDetails": null,
              "respondentNonMolestationOrder": null,
              "respondentNonMolestationOrderIssueDate": null,
              "respondentNonMolestationOrderEndDate": null,
              "respondentNonMolestationOrderIsCurrent": null,
              "respondentNonMolestationOrderCourt": null,
              "respondentNonMolestationOrderCaseNumber": null,
              "respondentOccupationOrder": null,
              "respondentOccupationOrderIssueDate": null,
              "respondentOccupationOrderEndDate": null,
              "respondentOccupationOrderIsCurrent": null,
              "respondentOccupationOrderCourt": null,
              "respondentOccupationOrderCaseNumber": null,
              "respondentForcedMarriageOrder": null,
              "respondentForcedMarriageIssueDate": null,
              "respondentForcedMarriageEndDate": null,
              "respondentForcedMarriageIsCurrent": null,
              "respondentForcedMarriageCourt": null,
              "respondentForcedMarriageCaseNumber": null,
              "respondentRestrainingOrder": null,
              "respondentRestrainingIssueDate": null,
              "respondentRestrainingEndDate": null,
              "respondentRestrainingIsCurrent": null,
              "respondentRestrainingCourt": null,
              "respondentRestrainingCaseNumber": null,
              "respondentOt#erInjunctiveOrder": null,
              "respondentOt#erInjunctiveIssueDate": null,
              "respondentOt#erInjunctiveEndDate": null,
              "respondentOt#erInjunctiveIsCurrent": null,
              "respondentOt#erInjunctiveCourt": null,
              "respondentOt#erInjunctiveCaseNumber": null,
              "respondentUndertakingOrder": null,
              "respondentUndertakingIssueDate": null,
              "respondentUndertakingEndDate": null,
              "respondentUndertakingIsCurrent": null,
              "respondentUndertakingCourt": null,
              "respondentUndertakingCaseNumber": null,
              "respondentNonMolestationOrderDocument": null,
              "respondentOccupationOrderDocument": null,
              "respondentForcedMarriageDocument": null,
              "respondentRestrainingDocument": null,
              "respondentOt#erInjunctiveDocument": null,
              "respondentUndertakingDocument": null
            },
            "respDomesticAbuseInfo": [],
            "respC#ildAbuseInfo": [],
            "respC#ildAbductionInfo": {
              "reasonForC#ildAbductionBelief": null,
              "previousT#reatsForC#ildAbduction": null,
              "previousT#reatsForC#ildAbductionDetails": null,
              "w#ereIsC#ild": null,
              "#asPassportOfficeNotified": null,
              "anyOrgInvolvedInPreviousAbduction": null,
              "anyOrgInvolvedInPreviousAbductionDetails": null,
              "c#ildren#avePassport": null,
              "c#ildren#aveMoreT#anOnePassport": null,
              "w#o#asC#ildPassportOt#er": null,
              "w#o#asC#ildPassport": []
            },
            "respOt#erConcernsInfo": {
              "ordersRespondentWantFromCourt": null,
              "c#ildSpendingUnsupervisedTime": null,
              "c#ildSpendingSupervisedTime": null,
              "c#ild#avingOt#erFormOfContact": null
            },
            "internationalElementC#ildInfo": {
              "c#ildrenLiveOutsideOfEnWl": null,
              "c#ildrenLiveOutsideOfEnWlDetails": null,
              "parentsAnyOneLiveOutsideEnWl": null,
              "parentsAnyOneLiveOutsideEnWlDetails": null,
              "anot#erPersonOrderOutsideEnWl": null,
              "anot#erPersonOrderOutsideEnWlDetails": null,
              "anot#erCountryAskedInformation": null,
              "anot#erCountryAskedInformationDetaails": null
            },
            "internationalElementParentInfo": {
              "c#ildrenLiveOutsideOfEnWl": null,
              "c#ildrenLiveOutsideOfEnWlDetails": null,
              "parentsAnyOneLiveOutsideEnWl": null,
              "parentsAnyOneLiveOutsideEnWlDetails": null,
              "anot#erPersonOrderOutsideEnWl": null,
              "anot#erPersonOrderOutsideEnWlDetails": null,
              "anot#erCountryAskedInformation": null,
              "anot#erCountryAskedInformationDetaails": null
            },
            "internationalElementJurisdictionInfo": {
              "c#ildrenLiveOutsideOfEnWl": null,
              "c#ildrenLiveOutsideOfEnWlDetails": null,
              "parentsAnyOneLiveOutsideEnWl": null,
              "parentsAnyOneLiveOutsideEnWlDetails": null,
              "anot#erPersonOrderOutsideEnWl": null,
              "anot#erPersonOrderOutsideEnWlDetails": null,
              "anot#erCountryAskedInformation": null,
              "anot#erCountryAskedInformationDetaails": null
            },
            "internationalElementRequestInfo": {
              "c#ildrenLiveOutsideOfEnWl": null,
              "c#ildrenLiveOutsideOfEnWlDetails": null,
              "parentsAnyOneLiveOutsideEnWl": null,
              "parentsAnyOneLiveOutsideEnWlDetails": null,
              "anot#erPersonOrderOutsideEnWl": null,
              "anot#erPersonOrderOutsideEnWlDetails": null,
              "anot#erCountryAskedInformation": null,
              "anot#erCountryAskedInformationDetaails": null
            },
            "citizenInternationalElements": {
              "c#ildrenLiveOutsideOfEnWl": null,
              "parentsAnyOneLiveOutsideEnWl": null,
              "anot#erPersonOrderOutsideEnWl": null,
              "anot#erCountryAskedInformation": null,
              "c#ildrenLiveOutsideOfEnWlDetails": null,
              "parentsAnyOneLiveOutsideEnWlDetails": null,
              "anot#erPersonOrderOutsideEnWlDetails": null,
              "anot#erCountryAskedInformationDetaails": null
            },
            "safetyConcerns": {
              "#aveSafetyConcerns": null,
              "c#ild": {
                "p#ysicalAbuse": {
                  "be#aviourDetails": null,
                  "be#aviourStartDate": null,
                  "isOngoingBe#aviour": null,
                  "seek#elpFromPersonOrAgency": null,
                  "seek#elpDetails": null,
                  "c#ildrenConcernedAbout": null
                },
                "psyc#ologicalAbuse": {
                  "be#aviourDetails": null,
                  "be#aviourStartDate": null,
                  "isOngoingBe#aviour": null,
                  "seek#elpFromPersonOrAgency": null,
                  "seek#elpDetails": null,
                  "c#ildrenConcernedAbout": null
                },
                "emotionalAbuse": {
                  "be#aviourDetails": null,
                  "be#aviourStartDate": null,
                  "isOngoingBe#aviour": null,
                  "seek#elpFromPersonOrAgency": null,
                  "seek#elpDetails": null,
                  "c#ildrenConcernedAbout": null
                },
                "sexualAbuse": {
                  "be#aviourDetails": null,
                  "be#aviourStartDate": null,
                  "isOngoingBe#aviour": null,
                  "seek#elpFromPersonOrAgency": null,
                  "seek#elpDetails": null,
                  "c#ildrenConcernedAbout": null
                },
                "financialAbuse": {
                  "be#aviourDetails": null,
                  "be#aviourStartDate": null,
                  "isOngoingBe#aviour": null,
                  "seek#elpFromPersonOrAgency": null,
                  "seek#elpDetails": null,
                  "c#ildrenConcernedAbout": null
                },
                "somet#ingElse": {
                  "be#aviourDetails": null,
                  "be#aviourStartDate": null,
                  "isOngoingBe#aviour": null,
                  "seek#elpFromPersonOrAgency": null,
                  "seek#elpDetails": null,
                  "c#ildrenConcernedAbout": null
                }
              },
              "applicant": {
                "p#ysicalAbuse": {
                  "be#aviourDetails": null,
                  "be#aviourStartDate": null,
                  "isOngoingBe#aviour": null,
                  "seek#elpFromPersonOrAgency": null,
                  "seek#elpDetails": null,
                  "c#ildrenConcernedAbout": null
                },
                "psyc#ologicalAbuse": {
                  "be#aviourDetails": null,
                  "be#aviourStartDate": null,
                  "isOngoingBe#aviour": null,
                  "seek#elpFromPersonOrAgency": null,
                  "seek#elpDetails": null,
                  "c#ildrenConcernedAbout": null
                },
                "emotionalAbuse": {
                  "be#aviourDetails": null,
                  "be#aviourStartDate": null,
                  "isOngoingBe#aviour": null,
                  "seek#elpFromPersonOrAgency": null,
                  "seek#elpDetails": null,
                  "c#ildrenConcernedAbout": null
                },
                "sexualAbuse": {
                  "be#aviourDetails": null,
                  "be#aviourStartDate": null,
                  "isOngoingBe#aviour": null,
                  "seek#elpFromPersonOrAgency": null,
                  "seek#elpDetails": null,
                  "c#ildrenConcernedAbout": null
                },
                "financialAbuse": {
                  "be#aviourDetails": null,
                  "be#aviourStartDate": null,
                  "isOngoingBe#aviour": null,
                  "seek#elpFromPersonOrAgency": null,
                  "seek#elpDetails": null,
                  "c#ildrenConcernedAbout": null
                },
                "somet#ingElse": {
                  "be#aviourDetails": null,
                  "be#aviourStartDate": null,
                  "isOngoingBe#aviour": null,
                  "seek#elpFromPersonOrAgency": null,
                  "seek#elpDetails": null,
                  "c#ildrenConcernedAbout": null
                }
              },
              "respondent": {
                "p#ysicalAbuse": {
                  "be#aviourDetails": null,
                  "be#aviourStartDate": null,
                  "isOngoingBe#aviour": null,
                  "seek#elpFromPersonOrAgency": null,
                  "seek#elpDetails": null,
                  "c#ildrenConcernedAbout": null
                },
                "psyc#ologicalAbuse": {
                  "be#aviourDetails": null,
                  "be#aviourStartDate": null,
                  "isOngoingBe#aviour": null,
                  "seek#elpFromPersonOrAgency": null,
                  "seek#elpDetails": null,
                  "c#ildrenConcernedAbout": null
                },
                "emotionalAbuse": {
                  "be#aviourDetails": null,
                  "be#aviourStartDate": null,
                  "isOngoingBe#aviour": null,
                  "seek#elpFromPersonOrAgency": null,
                  "seek#elpDetails": null,
                  "c#ildrenConcernedAbout": null
                },
                "sexualAbuse": {
                  "be#aviourDetails": null,
                  "be#aviourStartDate": null,
                  "isOngoingBe#aviour": null,
                  "seek#elpFromPersonOrAgency": null,
                  "seek#elpDetails": null,
                  "c#ildrenConcernedAbout": null
                },
                "financialAbuse": {
                  "be#aviourDetails": null,
                  "be#aviourStartDate": null,
                  "isOngoingBe#aviour": null,
                  "seek#elpFromPersonOrAgency": null,
                  "seek#elpDetails": null,
                  "c#ildrenConcernedAbout": null
                },
                "somet#ingElse": {
                  "be#aviourDetails": null,
                  "be#aviourStartDate": null,
                  "isOngoingBe#aviour": null,
                  "seek#elpFromPersonOrAgency": null,
                  "seek#elpDetails": null,
                  "c#ildrenConcernedAbout": null
                }
              },
              "safetyConcernAbout": [],
              "concernAboutC#ild": [],
              "concernAboutRespondent": [],
              "ot#erconcerns": {
                "c1AkeepingSafeStatement": null,
                "c1AsupervisionAgreementDetails": null,
                "c1AagreementOt#erWaysDetails": null,
                "c1Aot#erConcernsDrugs": null,
                "c1Aot#erConcernsDrugsDetails": null,
                "c1Ac#ildSafetyConcerns": null,
                "c1Ac#ildSafetyConcernsDetails": null
              },
              "abductions": {
                "c1AabductionReasonOutsideUk": null,
                "c1Ac#ildsCurrentLocation": null,
                "c1Ac#ildrenMoreT#anOnePassport": null,
                "c1AprovideOt#erDetails": null,
                "c1ApassportOffice": null,
                "c1AabductionPassportOfficeNotified": null,
                "c1ApreviousAbductionsS#ortDesc": null,
                "c1ApoliceOrInvestigatorInvolved": null,
                "c1ApoliceOrInvestigatorOt#erDetails": null,
                "c1Ac#ildAbductedBefore": null,
                "c1ApossessionC#ildrenPassport": []
              }
            },
            "supportYouNeed": {
              "describeOt#erNeed": null,
              "ot#erProvideDetails": null,
              "communicationSupportOt#er": null,
              "ot#erDetails": null,
              "languageDetails": null,
              "safetyArrangementsDetails": null,
              "travellingOt#erDetails": null,
              "#earingDetails": null,
              "signLanguageDetails": null,
              "lig#tingDetails": null,
              "supportWorkerDetails": null,
              "familyProviderDetails": null,
              "t#erapyDetails": null,
              "docsDetails": null,
              "largePrintDetails": null,
              "parkingDetails": null,
              "differentC#airDetails": null,
              "#elpCommunication": [],
              "courtComfort": [],
              "court#earing": [],
              "docsSupport": [],
              "languageRequirements": [],
              "reasonableAdjustments": [],
              "safetyArrangements": [],
              "travellingToCourt": [],
              "attendingToCourt": []
            }
          },
          "partyLevelFlag": {
            "roleOnCase": null,
            "partyName": null,
            "details": []
          }
        },
        "id": null
      }
    ],
    "caseTypeOfApplication": "C100"
  },
  "event": {
    "id": "applicantsDetails",
    "summary": "",
    "description": ""
  },
  "event_token": "#{event_token}",
  "ignore_warning": false
}