{
    "name": "All Requests",
    "numberOfRequests": {
        "total": 11,
        "ok": 10,
        "ko": 1
    },
    "minResponseTime": {
        "total": 61,
        "ok": 61,
        "ko": 307
    },
    "maxResponseTime": {
        "total": 16762,
        "ok": 16762,
        "ko": 307
    },
    "meanResponseTime": {
        "total": 2520,
        "ok": 2741,
        "ko": 307
    },
    "standardDeviation": {
        "total": 5069,
        "ok": 5265,
        "ko": 0
    },
    "percentiles1": {
        "total": 219,
        "ok": 198,
        "ko": 307
    },
    "percentiles2": {
        "total": 770,
        "ok": 859,
        "ko": 307
    },
    "percentiles3": {
        "total": 12566,
        "ok": 12985,
        "ko": 307
    },
    "percentiles4": {
        "total": 15923,
        "ok": 16007,
        "ko": 307
    },
    "group1": {
    "name": "t < 800 ms",
    "htmlName": "t < 800 ms",
    "count": 7,
    "percentage": 64
},
    "group2": {
    "name": "800 ms <= t < 1200 ms",
    "htmlName": "t >= 800 ms <br> t < 1200 ms",
    "count": 1,
    "percentage": 9
},
    "group3": {
    "name": "t >= 1200 ms",
    "htmlName": "t >= 1200 ms",
    "count": 2,
    "percentage": 18
},
    "group4": {
    "name": "failed",
    "htmlName": "failed",
    "count": 1,
    "percentage": 9
},
    "meanNumberOfRequestsPerSecond": {
        "total": 0.3793103448275862,
        "ok": 0.3448275862068966,
        "ko": 0.034482758620689655
    }
}